{
  "version": 1,
  "subject": "生命保険計理",
  "subjectSlug": "seiho-keiri-math",
  "year": 2024,
  "form": "A",
  "updatedAt": "2026-06-28T02:17:38.845Z",
  "questions": [
    {
      "id": "2024-A-seiho-keiri-001",
      "subject": "生命保険計理",
      "year": 2024,
      "form": "A",
      "questionNumber": 1,
      "category": "生命保険と死亡表",
      "questionType": "語群選択",
      "question": "次の文章の空欄［1］に入る最も適切なものを選んでください。\n\n［生存率・生存数・平均余命・保険料計算］                    語群\n文中の空欄［ １ ］～［ ５ ］に入る最も適切な数値を選んでください。     ア．0.98643\n\n(1) ＜付表１＞の生保標準生命表2018（死亡保険用）\n（男）を用いて計算す   イ．0.98925\n\nると、                                    ウ．1.16\n①45歳の男子が50歳まで生存する確率は、［ １ ］である。（解答は小数\n第６位四捨五入）                              エ．1.81\n\n②55歳の男子が10万人いる。10年後に生存している人数は、\n［ ２ ］人で   オ．14,200\nある。（解答は小数第１位四捨五入）\n③105歳の男子の平均余命は、\n［ ３ ］年である。\n（計算過程および計算結     カ．15,440\n\n果は小数第３位四捨五入）                          キ．92,763\n(2) ＜付表１＞の生保標準生命表2018（死亡保険用）\n（男）、＜付表２＞の\n複利表・複利現価表（年1.0％）を用いて計算すると、             ク．93,714\n\n①保険金500万円、男子50歳加入の１年定期保険の純保険料の計算におい    ケ．1,361,386\nて、死亡者全員分に対して支払われる保険金総額の現価は、\n［ ４ ］千\n円である。\n（解答は千円未満四捨五入）                     コ．1,368,176\n\n②純保険料は、\n［ ５ ］円である。\n（解答は10円未満四捨五入）",
      "choices": [
        {
          "label": "ア",
          "text": "0.98643"
        },
        {
          "label": "イ",
          "text": "0.98925"
        },
        {
          "label": "ウ",
          "text": "1.16"
        },
        {
          "label": "エ",
          "text": "1.81"
        },
        {
          "label": "オ",
          "text": "14,200"
        },
        {
          "label": "カ",
          "text": "15,440"
        },
        {
          "label": "キ",
          "text": "92,763"
        },
        {
          "label": "ク",
          "text": "93,714"
        },
        {
          "label": "ケ",
          "text": "1,361,386"
        },
        {
          "label": "コ",
          "text": "1,368,176"
        }
      ],
      "answer": "イ",
      "answerText": "0.98925",
      "explanation": "空欄［1］は「0.98925」。本文の計算条件・用語定義に照らして、この選択肢が該当する。",
      "keyPoint": "空欄［1］は「0.98925」。計算問題では使用する付表・利率・丸め条件を確認する。",
      "commonMistake": "問題文の数値条件、付表番号、端数処理を読み落とさない。",
      "difficulty": "標準",
      "tags": [
        "2024年度",
        "フォームA",
        "生命保険計理"
      ],
      "chapter": "第1章 生命保険と死亡表",
      "section": "死亡表の見方・平均余命",
      "evidence": {
        "textbook": "2026年版 生命保険講座 生命保険計理",
        "chapter": "第1章 生命保険と死亡表",
        "section": "死亡表の見方・平均余命",
        "page": "4-17",
        "quote": "死亡表の見方・平均余命に関する本文・例題・付表を根拠に確認。"
      }
    },
    {
      "id": "2024-A-seiho-keiri-002",
      "subject": "生命保険計理",
      "year": 2024,
      "form": "A",
      "questionNumber": 2,
      "category": "生命保険と死亡表",
      "questionType": "語群選択",
      "question": "次の文章の空欄［2］に入る最も適切なものを選んでください。\n\n［生存率・生存数・平均余命・保険料計算］                    語群\n文中の空欄［ １ ］～［ ５ ］に入る最も適切な数値を選んでください。     ア．0.98643\n\n(1) ＜付表１＞の生保標準生命表2018（死亡保険用）\n（男）を用いて計算す   イ．0.98925\n\nると、                                    ウ．1.16\n①45歳の男子が50歳まで生存する確率は、［ １ ］である。（解答は小数\n第６位四捨五入）                              エ．1.81\n\n②55歳の男子が10万人いる。10年後に生存している人数は、\n［ ２ ］人で   オ．14,200\nある。（解答は小数第１位四捨五入）\n③105歳の男子の平均余命は、\n［ ３ ］年である。\n（計算過程および計算結     カ．15,440\n\n果は小数第３位四捨五入）                          キ．92,763\n(2) ＜付表１＞の生保標準生命表2018（死亡保険用）\n（男）、＜付表２＞の\n複利表・複利現価表（年1.0％）を用いて計算すると、             ク．93,714\n\n①保険金500万円、男子50歳加入の１年定期保険の純保険料の計算におい    ケ．1,361,386\nて、死亡者全員分に対して支払われる保険金総額の現価は、\n［ ４ ］千\n円である。\n（解答は千円未満四捨五入）                     コ．1,368,176\n\n②純保険料は、\n［ ５ ］円である。\n（解答は10円未満四捨五入）",
      "choices": [
        {
          "label": "ア",
          "text": "0.98643"
        },
        {
          "label": "イ",
          "text": "0.98925"
        },
        {
          "label": "ウ",
          "text": "1.16"
        },
        {
          "label": "エ",
          "text": "1.81"
        },
        {
          "label": "オ",
          "text": "14,200"
        },
        {
          "label": "カ",
          "text": "15,440"
        },
        {
          "label": "キ",
          "text": "92,763"
        },
        {
          "label": "ク",
          "text": "93,714"
        },
        {
          "label": "ケ",
          "text": "1,361,386"
        },
        {
          "label": "コ",
          "text": "1,368,176"
        }
      ],
      "answer": "ク",
      "answerText": "93,714",
      "explanation": "空欄［2］は「93,714」。本文の計算条件・用語定義に照らして、この選択肢が該当する。",
      "keyPoint": "空欄［2］は「93,714」。計算問題では使用する付表・利率・丸め条件を確認する。",
      "commonMistake": "問題文の数値条件、付表番号、端数処理を読み落とさない。",
      "difficulty": "標準",
      "tags": [
        "2024年度",
        "フォームA",
        "生命保険計理"
      ],
      "chapter": "第1章 生命保険と死亡表",
      "section": "死亡表の見方・平均余命",
      "evidence": {
        "textbook": "2026年版 生命保険講座 生命保険計理",
        "chapter": "第1章 生命保険と死亡表",
        "section": "死亡表の見方・平均余命",
        "page": "4-17",
        "quote": "死亡表の見方・平均余命に関する本文・例題・付表を根拠に確認。"
      }
    },
    {
      "id": "2024-A-seiho-keiri-003",
      "subject": "生命保険計理",
      "year": 2024,
      "form": "A",
      "questionNumber": 3,
      "category": "生命保険と死亡表",
      "questionType": "語群選択",
      "question": "次の文章の空欄［3］に入る最も適切なものを選んでください。\n\n［生存率・生存数・平均余命・保険料計算］                    語群\n文中の空欄［ １ ］～［ ５ ］に入る最も適切な数値を選んでください。     ア．0.98643\n\n(1) ＜付表１＞の生保標準生命表2018（死亡保険用）\n（男）を用いて計算す   イ．0.98925\n\nると、                                    ウ．1.16\n①45歳の男子が50歳まで生存する確率は、［ １ ］である。（解答は小数\n第６位四捨五入）                              エ．1.81\n\n②55歳の男子が10万人いる。10年後に生存している人数は、\n［ ２ ］人で   オ．14,200\nある。（解答は小数第１位四捨五入）\n③105歳の男子の平均余命は、\n［ ３ ］年である。\n（計算過程および計算結     カ．15,440\n\n果は小数第３位四捨五入）                          キ．92,763\n(2) ＜付表１＞の生保標準生命表2018（死亡保険用）\n（男）、＜付表２＞の\n複利表・複利現価表（年1.0％）を用いて計算すると、             ク．93,714\n\n①保険金500万円、男子50歳加入の１年定期保険の純保険料の計算におい    ケ．1,361,386\nて、死亡者全員分に対して支払われる保険金総額の現価は、\n［ ４ ］千\n円である。\n（解答は千円未満四捨五入）                     コ．1,368,176\n\n②純保険料は、\n［ ５ ］円である。\n（解答は10円未満四捨五入）",
      "choices": [
        {
          "label": "ア",
          "text": "0.98643"
        },
        {
          "label": "イ",
          "text": "0.98925"
        },
        {
          "label": "ウ",
          "text": "1.16"
        },
        {
          "label": "エ",
          "text": "1.81"
        },
        {
          "label": "オ",
          "text": "14,200"
        },
        {
          "label": "カ",
          "text": "15,440"
        },
        {
          "label": "キ",
          "text": "92,763"
        },
        {
          "label": "ク",
          "text": "93,714"
        },
        {
          "label": "ケ",
          "text": "1,361,386"
        },
        {
          "label": "コ",
          "text": "1,368,176"
        }
      ],
      "answer": "ウ",
      "answerText": "1.16",
      "explanation": "空欄［3］は「1.16」。本文の計算条件・用語定義に照らして、この選択肢が該当する。",
      "keyPoint": "空欄［3］は「1.16」。計算問題では使用する付表・利率・丸め条件を確認する。",
      "commonMistake": "問題文の数値条件、付表番号、端数処理を読み落とさない。",
      "difficulty": "標準",
      "tags": [
        "2024年度",
        "フォームA",
        "生命保険計理"
      ],
      "chapter": "第1章 生命保険と死亡表",
      "section": "死亡表の見方・平均余命",
      "evidence": {
        "textbook": "2026年版 生命保険講座 生命保険計理",
        "chapter": "第1章 生命保険と死亡表",
        "section": "死亡表の見方・平均余命",
        "page": "4-17",
        "quote": "死亡表の見方・平均余命に関する本文・例題・付表を根拠に確認。"
      }
    },
    {
      "id": "2024-A-seiho-keiri-004",
      "subject": "生命保険計理",
      "year": 2024,
      "form": "A",
      "questionNumber": 4,
      "category": "生命保険と死亡表",
      "questionType": "語群選択",
      "question": "次の文章の空欄［4］に入る最も適切なものを選んでください。\n\n［生存率・生存数・平均余命・保険料計算］                    語群\n文中の空欄［ １ ］～［ ５ ］に入る最も適切な数値を選んでください。     ア．0.98643\n\n(1) ＜付表１＞の生保標準生命表2018（死亡保険用）\n（男）を用いて計算す   イ．0.98925\n\nると、                                    ウ．1.16\n①45歳の男子が50歳まで生存する確率は、［ １ ］である。（解答は小数\n第６位四捨五入）                              エ．1.81\n\n②55歳の男子が10万人いる。10年後に生存している人数は、\n［ ２ ］人で   オ．14,200\nある。（解答は小数第１位四捨五入）\n③105歳の男子の平均余命は、\n［ ３ ］年である。\n（計算過程および計算結     カ．15,440\n\n果は小数第３位四捨五入）                          キ．92,763\n(2) ＜付表１＞の生保標準生命表2018（死亡保険用）\n（男）、＜付表２＞の\n複利表・複利現価表（年1.0％）を用いて計算すると、             ク．93,714\n\n①保険金500万円、男子50歳加入の１年定期保険の純保険料の計算におい    ケ．1,361,386\nて、死亡者全員分に対して支払われる保険金総額の現価は、\n［ ４ ］千\n円である。\n（解答は千円未満四捨五入）                     コ．1,368,176\n\n②純保険料は、\n［ ５ ］円である。\n（解答は10円未満四捨五入）",
      "choices": [
        {
          "label": "ア",
          "text": "0.98643"
        },
        {
          "label": "イ",
          "text": "0.98925"
        },
        {
          "label": "ウ",
          "text": "1.16"
        },
        {
          "label": "エ",
          "text": "1.81"
        },
        {
          "label": "オ",
          "text": "14,200"
        },
        {
          "label": "カ",
          "text": "15,440"
        },
        {
          "label": "キ",
          "text": "92,763"
        },
        {
          "label": "ク",
          "text": "93,714"
        },
        {
          "label": "ケ",
          "text": "1,361,386"
        },
        {
          "label": "コ",
          "text": "1,368,176"
        }
      ],
      "answer": "コ",
      "answerText": "1,368,176",
      "explanation": "空欄［4］は「1,368,176」。本文の計算条件・用語定義に照らして、この選択肢が該当する。",
      "keyPoint": "空欄［4］は「1,368,176」。計算問題では使用する付表・利率・丸め条件を確認する。",
      "commonMistake": "問題文の数値条件、付表番号、端数処理を読み落とさない。",
      "difficulty": "標準",
      "tags": [
        "2024年度",
        "フォームA",
        "生命保険計理"
      ],
      "chapter": "第1章 生命保険と死亡表",
      "section": "死亡表の見方・平均余命",
      "evidence": {
        "textbook": "2026年版 生命保険講座 生命保険計理",
        "chapter": "第1章 生命保険と死亡表",
        "section": "死亡表の見方・平均余命",
        "page": "4-17",
        "quote": "死亡表の見方・平均余命に関する本文・例題・付表を根拠に確認。"
      }
    },
    {
      "id": "2024-A-seiho-keiri-005",
      "subject": "生命保険計理",
      "year": 2024,
      "form": "A",
      "questionNumber": 5,
      "category": "生命保険と死亡表",
      "questionType": "語群選択",
      "question": "次の文章の空欄［5］に入る最も適切なものを選んでください。\n\n［生存率・生存数・平均余命・保険料計算］                    語群\n文中の空欄［ １ ］～［ ５ ］に入る最も適切な数値を選んでください。     ア．0.98643\n\n(1) ＜付表１＞の生保標準生命表2018（死亡保険用）\n（男）を用いて計算す   イ．0.98925\n\nると、                                    ウ．1.16\n①45歳の男子が50歳まで生存する確率は、［ １ ］である。（解答は小数\n第６位四捨五入）                              エ．1.81\n\n②55歳の男子が10万人いる。10年後に生存している人数は、\n［ ２ ］人で   オ．14,200\nある。（解答は小数第１位四捨五入）\n③105歳の男子の平均余命は、\n［ ３ ］年である。\n（計算過程および計算結     カ．15,440\n\n果は小数第３位四捨五入）                          キ．92,763\n(2) ＜付表１＞の生保標準生命表2018（死亡保険用）\n（男）、＜付表２＞の\n複利表・複利現価表（年1.0％）を用いて計算すると、             ク．93,714\n\n①保険金500万円、男子50歳加入の１年定期保険の純保険料の計算におい    ケ．1,361,386\nて、死亡者全員分に対して支払われる保険金総額の現価は、\n［ ４ ］千\n円である。\n（解答は千円未満四捨五入）                     コ．1,368,176\n\n②純保険料は、\n［ ５ ］円である。\n（解答は10円未満四捨五入）",
      "choices": [
        {
          "label": "ア",
          "text": "0.98643"
        },
        {
          "label": "イ",
          "text": "0.98925"
        },
        {
          "label": "ウ",
          "text": "1.16"
        },
        {
          "label": "エ",
          "text": "1.81"
        },
        {
          "label": "オ",
          "text": "14,200"
        },
        {
          "label": "カ",
          "text": "15,440"
        },
        {
          "label": "キ",
          "text": "92,763"
        },
        {
          "label": "ク",
          "text": "93,714"
        },
        {
          "label": "ケ",
          "text": "1,361,386"
        },
        {
          "label": "コ",
          "text": "1,368,176"
        }
      ],
      "answer": "オ",
      "answerText": "14,200",
      "explanation": "空欄［5］は「14,200」。本文の計算条件・用語定義に照らして、この選択肢が該当する。",
      "keyPoint": "空欄［5］は「14,200」。計算問題では使用する付表・利率・丸め条件を確認する。",
      "commonMistake": "問題文の数値条件、付表番号、端数処理を読み落とさない。",
      "difficulty": "標準",
      "tags": [
        "2024年度",
        "フォームA",
        "生命保険計理"
      ],
      "chapter": "第1章 生命保険と死亡表",
      "section": "死亡表の見方・平均余命",
      "evidence": {
        "textbook": "2026年版 生命保険講座 生命保険計理",
        "chapter": "第1章 生命保険と死亡表",
        "section": "死亡表の見方・平均余命",
        "page": "4-17",
        "quote": "死亡表の見方・平均余命に関する本文・例題・付表を根拠に確認。"
      }
    },
    {
      "id": "2024-A-seiho-keiri-006",
      "subject": "生命保険計理",
      "year": 2024,
      "form": "A",
      "questionNumber": 6,
      "category": "現価と終価",
      "questionType": "語群選択",
      "question": "次の文章の空欄［6］に入る最も適切なものを選んでください。\n\n［複利運用］                                   語群\n文中の空欄［ ６ ］～［ 10 ］に入る最も適切な数値を選んでください。     ア．1.21\n\n(1) 元金50万円とした場合、                         イ．1.51\n\n①月利率0.15％、１カ月複利で運用した場合の半年後の利息は、［ ６ ］    ウ．1.83\n円である。\n（解答は円未満四捨五入）\n②年利率1.4％、半年複利で計算したときの４年後の元利合計額は、\n［ ７ ］    エ．1.85\n\n円である。\n（解答は円未満四捨五入）                       オ．4,517\n(2) 名称利率1.2％、転化回数４回により複利計算した場合、元金１の実利\n率は、\n［ ８ ］％である。\n（解答は小数第３位四捨五入）               カ．5,274\n\n(3) 300万円を年1.8％の複利で３年間運用した場合の年平均利回りは、    キ．528,594\n［ ９ ］％である。\n（解答は小数第３位四捨五入）\n(4) 年利率1.6％の複利で５年後（期末）に500万円を得ようとする場合、   ク．528,696\n\n現在必要な資金は、\n［ 10 ］円である。\n（解答は円未満四捨五入）          ケ．4,545,773\n\nコ．4,618,507",
      "choices": [
        {
          "label": "ア",
          "text": "1.21"
        },
        {
          "label": "イ",
          "text": "1.51"
        },
        {
          "label": "ウ",
          "text": "1.83"
        },
        {
          "label": "エ",
          "text": "1.85"
        },
        {
          "label": "オ",
          "text": "4,517"
        },
        {
          "label": "カ",
          "text": "5,274"
        },
        {
          "label": "キ",
          "text": "528,594"
        },
        {
          "label": "ク",
          "text": "528,696"
        },
        {
          "label": "ケ",
          "text": "4,545,773"
        },
        {
          "label": "コ",
          "text": "4,618,507"
        }
      ],
      "answer": "オ",
      "answerText": "4,517",
      "explanation": "空欄［6］は「4,517」。本文の計算条件・用語定義に照らして、この選択肢が該当する。",
      "keyPoint": "空欄［6］は「4,517」。計算問題では使用する付表・利率・丸め条件を確認する。",
      "commonMistake": "問題文の数値条件、付表番号、端数処理を読み落とさない。",
      "difficulty": "標準",
      "tags": [
        "2024年度",
        "フォームA",
        "生命保険計理"
      ],
      "chapter": "第2章 現価と終価",
      "section": "利息計算・現価と終価",
      "evidence": {
        "textbook": "2026年版 生命保険講座 生命保険計理",
        "chapter": "第2章 現価と終価",
        "section": "利息計算・現価と終価",
        "page": "19-31",
        "quote": "利息計算・現価と終価に関する本文・例題・付表を根拠に確認。"
      }
    },
    {
      "id": "2024-A-seiho-keiri-007",
      "subject": "生命保険計理",
      "year": 2024,
      "form": "A",
      "questionNumber": 7,
      "category": "現価と終価",
      "questionType": "語群選択",
      "question": "次の文章の空欄［7］に入る最も適切なものを選んでください。\n\n［複利運用］                                   語群\n文中の空欄［ ６ ］～［ 10 ］に入る最も適切な数値を選んでください。     ア．1.21\n\n(1) 元金50万円とした場合、                         イ．1.51\n\n①月利率0.15％、１カ月複利で運用した場合の半年後の利息は、［ ６ ］    ウ．1.83\n円である。\n（解答は円未満四捨五入）\n②年利率1.4％、半年複利で計算したときの４年後の元利合計額は、\n［ ７ ］    エ．1.85\n\n円である。\n（解答は円未満四捨五入）                       オ．4,517\n(2) 名称利率1.2％、転化回数４回により複利計算した場合、元金１の実利\n率は、\n［ ８ ］％である。\n（解答は小数第３位四捨五入）               カ．5,274\n\n(3) 300万円を年1.8％の複利で３年間運用した場合の年平均利回りは、    キ．528,594\n［ ９ ］％である。\n（解答は小数第３位四捨五入）\n(4) 年利率1.6％の複利で５年後（期末）に500万円を得ようとする場合、   ク．528,696\n\n現在必要な資金は、\n［ 10 ］円である。\n（解答は円未満四捨五入）          ケ．4,545,773\n\nコ．4,618,507",
      "choices": [
        {
          "label": "ア",
          "text": "1.21"
        },
        {
          "label": "イ",
          "text": "1.51"
        },
        {
          "label": "ウ",
          "text": "1.83"
        },
        {
          "label": "エ",
          "text": "1.85"
        },
        {
          "label": "オ",
          "text": "4,517"
        },
        {
          "label": "カ",
          "text": "5,274"
        },
        {
          "label": "キ",
          "text": "528,594"
        },
        {
          "label": "ク",
          "text": "528,696"
        },
        {
          "label": "ケ",
          "text": "4,545,773"
        },
        {
          "label": "コ",
          "text": "4,618,507"
        }
      ],
      "answer": "ク",
      "answerText": "528,696",
      "explanation": "空欄［7］は「528,696」。本文の計算条件・用語定義に照らして、この選択肢が該当する。",
      "keyPoint": "空欄［7］は「528,696」。計算問題では使用する付表・利率・丸め条件を確認する。",
      "commonMistake": "問題文の数値条件、付表番号、端数処理を読み落とさない。",
      "difficulty": "標準",
      "tags": [
        "2024年度",
        "フォームA",
        "生命保険計理"
      ],
      "chapter": "第2章 現価と終価",
      "section": "利息計算・現価と終価",
      "evidence": {
        "textbook": "2026年版 生命保険講座 生命保険計理",
        "chapter": "第2章 現価と終価",
        "section": "利息計算・現価と終価",
        "page": "19-31",
        "quote": "利息計算・現価と終価に関する本文・例題・付表を根拠に確認。"
      }
    },
    {
      "id": "2024-A-seiho-keiri-008",
      "subject": "生命保険計理",
      "year": 2024,
      "form": "A",
      "questionNumber": 8,
      "category": "現価と終価",
      "questionType": "語群選択",
      "question": "次の文章の空欄［8］に入る最も適切なものを選んでください。\n\n［複利運用］                                   語群\n文中の空欄［ ６ ］～［ 10 ］に入る最も適切な数値を選んでください。     ア．1.21\n\n(1) 元金50万円とした場合、                         イ．1.51\n\n①月利率0.15％、１カ月複利で運用した場合の半年後の利息は、［ ６ ］    ウ．1.83\n円である。\n（解答は円未満四捨五入）\n②年利率1.4％、半年複利で計算したときの４年後の元利合計額は、\n［ ７ ］    エ．1.85\n\n円である。\n（解答は円未満四捨五入）                       オ．4,517\n(2) 名称利率1.2％、転化回数４回により複利計算した場合、元金１の実利\n率は、\n［ ８ ］％である。\n（解答は小数第３位四捨五入）               カ．5,274\n\n(3) 300万円を年1.8％の複利で３年間運用した場合の年平均利回りは、    キ．528,594\n［ ９ ］％である。\n（解答は小数第３位四捨五入）\n(4) 年利率1.6％の複利で５年後（期末）に500万円を得ようとする場合、   ク．528,696\n\n現在必要な資金は、\n［ 10 ］円である。\n（解答は円未満四捨五入）          ケ．4,545,773\n\nコ．4,618,507",
      "choices": [
        {
          "label": "ア",
          "text": "1.21"
        },
        {
          "label": "イ",
          "text": "1.51"
        },
        {
          "label": "ウ",
          "text": "1.83"
        },
        {
          "label": "エ",
          "text": "1.85"
        },
        {
          "label": "オ",
          "text": "4,517"
        },
        {
          "label": "カ",
          "text": "5,274"
        },
        {
          "label": "キ",
          "text": "528,594"
        },
        {
          "label": "ク",
          "text": "528,696"
        },
        {
          "label": "ケ",
          "text": "4,545,773"
        },
        {
          "label": "コ",
          "text": "4,618,507"
        }
      ],
      "answer": "ア",
      "answerText": "1.21",
      "explanation": "空欄［8］は「1.21」。本文の計算条件・用語定義に照らして、この選択肢が該当する。",
      "keyPoint": "空欄［8］は「1.21」。計算問題では使用する付表・利率・丸め条件を確認する。",
      "commonMistake": "問題文の数値条件、付表番号、端数処理を読み落とさない。",
      "difficulty": "標準",
      "tags": [
        "2024年度",
        "フォームA",
        "生命保険計理"
      ],
      "chapter": "第2章 現価と終価",
      "section": "利息計算・現価と終価",
      "evidence": {
        "textbook": "2026年版 生命保険講座 生命保険計理",
        "chapter": "第2章 現価と終価",
        "section": "利息計算・現価と終価",
        "page": "19-31",
        "quote": "利息計算・現価と終価に関する本文・例題・付表を根拠に確認。"
      }
    },
    {
      "id": "2024-A-seiho-keiri-009",
      "subject": "生命保険計理",
      "year": 2024,
      "form": "A",
      "questionNumber": 9,
      "category": "現価と終価",
      "questionType": "語群選択",
      "question": "次の文章の空欄［9］に入る最も適切なものを選んでください。\n\n［複利運用］                                   語群\n文中の空欄［ ６ ］～［ 10 ］に入る最も適切な数値を選んでください。     ア．1.21\n\n(1) 元金50万円とした場合、                         イ．1.51\n\n①月利率0.15％、１カ月複利で運用した場合の半年後の利息は、［ ６ ］    ウ．1.83\n円である。\n（解答は円未満四捨五入）\n②年利率1.4％、半年複利で計算したときの４年後の元利合計額は、\n［ ７ ］    エ．1.85\n\n円である。\n（解答は円未満四捨五入）                       オ．4,517\n(2) 名称利率1.2％、転化回数４回により複利計算した場合、元金１の実利\n率は、\n［ ８ ］％である。\n（解答は小数第３位四捨五入）               カ．5,274\n\n(3) 300万円を年1.8％の複利で３年間運用した場合の年平均利回りは、    キ．528,594\n［ ９ ］％である。\n（解答は小数第３位四捨五入）\n(4) 年利率1.6％の複利で５年後（期末）に500万円を得ようとする場合、   ク．528,696\n\n現在必要な資金は、\n［ 10 ］円である。\n（解答は円未満四捨五入）          ケ．4,545,773\n\nコ．4,618,507",
      "choices": [
        {
          "label": "ア",
          "text": "1.21"
        },
        {
          "label": "イ",
          "text": "1.51"
        },
        {
          "label": "ウ",
          "text": "1.83"
        },
        {
          "label": "エ",
          "text": "1.85"
        },
        {
          "label": "オ",
          "text": "4,517"
        },
        {
          "label": "カ",
          "text": "5,274"
        },
        {
          "label": "キ",
          "text": "528,594"
        },
        {
          "label": "ク",
          "text": "528,696"
        },
        {
          "label": "ケ",
          "text": "4,545,773"
        },
        {
          "label": "コ",
          "text": "4,618,507"
        }
      ],
      "answer": "ウ",
      "answerText": "1.83",
      "explanation": "空欄［9］は「1.83」。本文の計算条件・用語定義に照らして、この選択肢が該当する。",
      "keyPoint": "空欄［9］は「1.83」。計算問題では使用する付表・利率・丸め条件を確認する。",
      "commonMistake": "問題文の数値条件、付表番号、端数処理を読み落とさない。",
      "difficulty": "標準",
      "tags": [
        "2024年度",
        "フォームA",
        "生命保険計理"
      ],
      "chapter": "第2章 現価と終価",
      "section": "利息計算・現価と終価",
      "evidence": {
        "textbook": "2026年版 生命保険講座 生命保険計理",
        "chapter": "第2章 現価と終価",
        "section": "利息計算・現価と終価",
        "page": "19-31",
        "quote": "利息計算・現価と終価に関する本文・例題・付表を根拠に確認。"
      }
    },
    {
      "id": "2024-A-seiho-keiri-010",
      "subject": "生命保険計理",
      "year": 2024,
      "form": "A",
      "questionNumber": 10,
      "category": "現価と終価",
      "questionType": "語群選択",
      "question": "次の文章の空欄［10］に入る最も適切なものを選んでください。\n\n［複利運用］                                   語群\n文中の空欄［ ６ ］～［ 10 ］に入る最も適切な数値を選んでください。     ア．1.21\n\n(1) 元金50万円とした場合、                         イ．1.51\n\n①月利率0.15％、１カ月複利で運用した場合の半年後の利息は、［ ６ ］    ウ．1.83\n円である。\n（解答は円未満四捨五入）\n②年利率1.4％、半年複利で計算したときの４年後の元利合計額は、\n［ ７ ］    エ．1.85\n\n円である。\n（解答は円未満四捨五入）                       オ．4,517\n(2) 名称利率1.2％、転化回数４回により複利計算した場合、元金１の実利\n率は、\n［ ８ ］％である。\n（解答は小数第３位四捨五入）               カ．5,274\n\n(3) 300万円を年1.8％の複利で３年間運用した場合の年平均利回りは、    キ．528,594\n［ ９ ］％である。\n（解答は小数第３位四捨五入）\n(4) 年利率1.6％の複利で５年後（期末）に500万円を得ようとする場合、   ク．528,696\n\n現在必要な資金は、\n［ 10 ］円である。\n（解答は円未満四捨五入）          ケ．4,545,773\n\nコ．4,618,507",
      "choices": [
        {
          "label": "ア",
          "text": "1.21"
        },
        {
          "label": "イ",
          "text": "1.51"
        },
        {
          "label": "ウ",
          "text": "1.83"
        },
        {
          "label": "エ",
          "text": "1.85"
        },
        {
          "label": "オ",
          "text": "4,517"
        },
        {
          "label": "カ",
          "text": "5,274"
        },
        {
          "label": "キ",
          "text": "528,594"
        },
        {
          "label": "ク",
          "text": "528,696"
        },
        {
          "label": "ケ",
          "text": "4,545,773"
        },
        {
          "label": "コ",
          "text": "4,618,507"
        }
      ],
      "answer": "コ",
      "answerText": "4,618,507",
      "explanation": "空欄［10］は「4,618,507」。本文の計算条件・用語定義に照らして、この選択肢が該当する。",
      "keyPoint": "空欄［10］は「4,618,507」。計算問題では使用する付表・利率・丸め条件を確認する。",
      "commonMistake": "問題文の数値条件、付表番号、端数処理を読み落とさない。",
      "difficulty": "標準",
      "tags": [
        "2024年度",
        "フォームA",
        "生命保険計理"
      ],
      "chapter": "第2章 現価と終価",
      "section": "利息計算・現価と終価",
      "evidence": {
        "textbook": "2026年版 生命保険講座 生命保険計理",
        "chapter": "第2章 現価と終価",
        "section": "利息計算・現価と終価",
        "page": "19-31",
        "quote": "利息計算・現価と終価に関する本文・例題・付表を根拠に確認。"
      }
    },
    {
      "id": "2024-A-seiho-keiri-011",
      "subject": "生命保険計理",
      "year": 2024,
      "form": "A",
      "questionNumber": 11,
      "category": "生命保険と死亡表",
      "questionType": "語群選択",
      "question": "次の文章の空欄［11］に入る最も適切なものを選んでください。\n\n［死亡表の種類］                                語群\n文中の空欄［ 11 ］～［ 15 ］に入る最も適切なものを選んでください。   ア．完全生命表\n\n死亡表は、国民あるいは特定地域の人口を対象として、その人口統計に       イ．基礎生命表\n\nよる死亡状況を表した「国民生命表」と、生命保険会社などの保険事業体       ウ．経験生命表\nが被保険者集団の実際の死亡統計に基づいて作成した「［ 11 ］」とに分け\nられる。                                    エ．告知効果\n\n「国民生命表」は、５年ごとの国勢調査による男女別、年齢別人口とそ       オ．全体生命表\nの時期の人口動態統計による男女別、年齢別死亡数を材料にして精緻な統\n計処理によって作成される「［ 12 ］」と、毎年の人口動態統計の死亡数と    カ．選択効果\n\n推計人口を用い、簡略化された計算によって算定された死亡率を表示する       キ．総合表\n「簡易生命表」とに分けられる。\n「\n［ 11 ］」は、経過年数による区別により、\n「［ 13 ］\n」と「選択表」とに   ク．地域別\n\n分けられる。                                  ケ．統一表\n「\n［ 13 ］」は、保険契約加入後の経過年数を考慮しないで全期間を対象\nに年齢別にまとめた死亡表であるが、生命保険会社では、健康状態等につ       コ．年齢別\n\nいての危険選択が行われた被保険者集団を対象としているので、一般には\n「国民生命表」よりも低い死亡率を示す。\nしかし、通常は加入後年数が経過するにつれて、それらの［ 14 ］が次\n第になくなり、死亡率は上昇する。そこで、この死亡率の変化を追跡でき\nるように［ 15 ］、経過年数別に死亡率を表示したものが「選択表」である。",
      "choices": [
        {
          "label": "ア",
          "text": "完全生命表"
        },
        {
          "label": "イ",
          "text": "基礎生命表"
        },
        {
          "label": "ウ",
          "text": "経験生命表"
        },
        {
          "label": "エ",
          "text": "告知効果"
        },
        {
          "label": "オ",
          "text": "全体生命表"
        },
        {
          "label": "カ",
          "text": "選択効果"
        },
        {
          "label": "キ",
          "text": "総合表"
        },
        {
          "label": "ク",
          "text": "地域別"
        },
        {
          "label": "ケ",
          "text": "統一表"
        },
        {
          "label": "コ",
          "text": "年齢別"
        }
      ],
      "answer": "ウ",
      "answerText": "経験生命表",
      "explanation": "空欄［11］は「経験生命表」。本文の計算条件・用語定義に照らして、この選択肢が該当する。",
      "keyPoint": "空欄［11］は「経験生命表」。計算問題では使用する付表・利率・丸め条件を確認する。",
      "commonMistake": "問題文の数値条件、付表番号、端数処理を読み落とさない。",
      "difficulty": "標準",
      "tags": [
        "2024年度",
        "フォームA",
        "生命保険計理"
      ],
      "chapter": "第1章 生命保険と死亡表",
      "section": "死亡表の種類",
      "evidence": {
        "textbook": "2026年版 生命保険講座 生命保険計理",
        "chapter": "第1章 生命保険と死亡表",
        "section": "死亡表の種類",
        "page": "4-17",
        "quote": "死亡表の種類に関する本文・例題・付表を根拠に確認。"
      }
    },
    {
      "id": "2024-A-seiho-keiri-012",
      "subject": "生命保険計理",
      "year": 2024,
      "form": "A",
      "questionNumber": 12,
      "category": "生命保険と死亡表",
      "questionType": "語群選択",
      "question": "次の文章の空欄［12］に入る最も適切なものを選んでください。\n\n［死亡表の種類］                                語群\n文中の空欄［ 11 ］～［ 15 ］に入る最も適切なものを選んでください。   ア．完全生命表\n\n死亡表は、国民あるいは特定地域の人口を対象として、その人口統計に       イ．基礎生命表\n\nよる死亡状況を表した「国民生命表」と、生命保険会社などの保険事業体       ウ．経験生命表\nが被保険者集団の実際の死亡統計に基づいて作成した「［ 11 ］」とに分け\nられる。                                    エ．告知効果\n\n「国民生命表」は、５年ごとの国勢調査による男女別、年齢別人口とそ       オ．全体生命表\nの時期の人口動態統計による男女別、年齢別死亡数を材料にして精緻な統\n計処理によって作成される「［ 12 ］」と、毎年の人口動態統計の死亡数と    カ．選択効果\n\n推計人口を用い、簡略化された計算によって算定された死亡率を表示する       キ．総合表\n「簡易生命表」とに分けられる。\n「\n［ 11 ］」は、経過年数による区別により、\n「［ 13 ］\n」と「選択表」とに   ク．地域別\n\n分けられる。                                  ケ．統一表\n「\n［ 13 ］」は、保険契約加入後の経過年数を考慮しないで全期間を対象\nに年齢別にまとめた死亡表であるが、生命保険会社では、健康状態等につ       コ．年齢別\n\nいての危険選択が行われた被保険者集団を対象としているので、一般には\n「国民生命表」よりも低い死亡率を示す。\nしかし、通常は加入後年数が経過するにつれて、それらの［ 14 ］が次\n第になくなり、死亡率は上昇する。そこで、この死亡率の変化を追跡でき\nるように［ 15 ］、経過年数別に死亡率を表示したものが「選択表」である。",
      "choices": [
        {
          "label": "ア",
          "text": "完全生命表"
        },
        {
          "label": "イ",
          "text": "基礎生命表"
        },
        {
          "label": "ウ",
          "text": "経験生命表"
        },
        {
          "label": "エ",
          "text": "告知効果"
        },
        {
          "label": "オ",
          "text": "全体生命表"
        },
        {
          "label": "カ",
          "text": "選択効果"
        },
        {
          "label": "キ",
          "text": "総合表"
        },
        {
          "label": "ク",
          "text": "地域別"
        },
        {
          "label": "ケ",
          "text": "統一表"
        },
        {
          "label": "コ",
          "text": "年齢別"
        }
      ],
      "answer": "ア",
      "answerText": "完全生命表",
      "explanation": "空欄［12］は「完全生命表」。本文の計算条件・用語定義に照らして、この選択肢が該当する。",
      "keyPoint": "空欄［12］は「完全生命表」。計算問題では使用する付表・利率・丸め条件を確認する。",
      "commonMistake": "問題文の数値条件、付表番号、端数処理を読み落とさない。",
      "difficulty": "標準",
      "tags": [
        "2024年度",
        "フォームA",
        "生命保険計理"
      ],
      "chapter": "第1章 生命保険と死亡表",
      "section": "死亡表の種類",
      "evidence": {
        "textbook": "2026年版 生命保険講座 生命保険計理",
        "chapter": "第1章 生命保険と死亡表",
        "section": "死亡表の種類",
        "page": "4-17",
        "quote": "死亡表の種類に関する本文・例題・付表を根拠に確認。"
      }
    },
    {
      "id": "2024-A-seiho-keiri-013",
      "subject": "生命保険計理",
      "year": 2024,
      "form": "A",
      "questionNumber": 13,
      "category": "生命保険と死亡表",
      "questionType": "語群選択",
      "question": "次の文章の空欄［13］に入る最も適切なものを選んでください。\n\n［死亡表の種類］                                語群\n文中の空欄［ 11 ］～［ 15 ］に入る最も適切なものを選んでください。   ア．完全生命表\n\n死亡表は、国民あるいは特定地域の人口を対象として、その人口統計に       イ．基礎生命表\n\nよる死亡状況を表した「国民生命表」と、生命保険会社などの保険事業体       ウ．経験生命表\nが被保険者集団の実際の死亡統計に基づいて作成した「［ 11 ］」とに分け\nられる。                                    エ．告知効果\n\n「国民生命表」は、５年ごとの国勢調査による男女別、年齢別人口とそ       オ．全体生命表\nの時期の人口動態統計による男女別、年齢別死亡数を材料にして精緻な統\n計処理によって作成される「［ 12 ］」と、毎年の人口動態統計の死亡数と    カ．選択効果\n\n推計人口を用い、簡略化された計算によって算定された死亡率を表示する       キ．総合表\n「簡易生命表」とに分けられる。\n「\n［ 11 ］」は、経過年数による区別により、\n「［ 13 ］\n」と「選択表」とに   ク．地域別\n\n分けられる。                                  ケ．統一表\n「\n［ 13 ］」は、保険契約加入後の経過年数を考慮しないで全期間を対象\nに年齢別にまとめた死亡表であるが、生命保険会社では、健康状態等につ       コ．年齢別\n\nいての危険選択が行われた被保険者集団を対象としているので、一般には\n「国民生命表」よりも低い死亡率を示す。\nしかし、通常は加入後年数が経過するにつれて、それらの［ 14 ］が次\n第になくなり、死亡率は上昇する。そこで、この死亡率の変化を追跡でき\nるように［ 15 ］、経過年数別に死亡率を表示したものが「選択表」である。",
      "choices": [
        {
          "label": "ア",
          "text": "完全生命表"
        },
        {
          "label": "イ",
          "text": "基礎生命表"
        },
        {
          "label": "ウ",
          "text": "経験生命表"
        },
        {
          "label": "エ",
          "text": "告知効果"
        },
        {
          "label": "オ",
          "text": "全体生命表"
        },
        {
          "label": "カ",
          "text": "選択効果"
        },
        {
          "label": "キ",
          "text": "総合表"
        },
        {
          "label": "ク",
          "text": "地域別"
        },
        {
          "label": "ケ",
          "text": "統一表"
        },
        {
          "label": "コ",
          "text": "年齢別"
        }
      ],
      "answer": "キ",
      "answerText": "総合表",
      "explanation": "空欄［13］は「総合表」。本文の計算条件・用語定義に照らして、この選択肢が該当する。",
      "keyPoint": "空欄［13］は「総合表」。計算問題では使用する付表・利率・丸め条件を確認する。",
      "commonMistake": "問題文の数値条件、付表番号、端数処理を読み落とさない。",
      "difficulty": "標準",
      "tags": [
        "2024年度",
        "フォームA",
        "生命保険計理"
      ],
      "chapter": "第1章 生命保険と死亡表",
      "section": "死亡表の種類",
      "evidence": {
        "textbook": "2026年版 生命保険講座 生命保険計理",
        "chapter": "第1章 生命保険と死亡表",
        "section": "死亡表の種類",
        "page": "4-17",
        "quote": "死亡表の種類に関する本文・例題・付表を根拠に確認。"
      }
    },
    {
      "id": "2024-A-seiho-keiri-014",
      "subject": "生命保険計理",
      "year": 2024,
      "form": "A",
      "questionNumber": 14,
      "category": "生命保険と死亡表",
      "questionType": "語群選択",
      "question": "次の文章の空欄［14］に入る最も適切なものを選んでください。\n\n［死亡表の種類］                                語群\n文中の空欄［ 11 ］～［ 15 ］に入る最も適切なものを選んでください。   ア．完全生命表\n\n死亡表は、国民あるいは特定地域の人口を対象として、その人口統計に       イ．基礎生命表\n\nよる死亡状況を表した「国民生命表」と、生命保険会社などの保険事業体       ウ．経験生命表\nが被保険者集団の実際の死亡統計に基づいて作成した「［ 11 ］」とに分け\nられる。                                    エ．告知効果\n\n「国民生命表」は、５年ごとの国勢調査による男女別、年齢別人口とそ       オ．全体生命表\nの時期の人口動態統計による男女別、年齢別死亡数を材料にして精緻な統\n計処理によって作成される「［ 12 ］」と、毎年の人口動態統計の死亡数と    カ．選択効果\n\n推計人口を用い、簡略化された計算によって算定された死亡率を表示する       キ．総合表\n「簡易生命表」とに分けられる。\n「\n［ 11 ］」は、経過年数による区別により、\n「［ 13 ］\n」と「選択表」とに   ク．地域別\n\n分けられる。                                  ケ．統一表\n「\n［ 13 ］」は、保険契約加入後の経過年数を考慮しないで全期間を対象\nに年齢別にまとめた死亡表であるが、生命保険会社では、健康状態等につ       コ．年齢別\n\nいての危険選択が行われた被保険者集団を対象としているので、一般には\n「国民生命表」よりも低い死亡率を示す。\nしかし、通常は加入後年数が経過するにつれて、それらの［ 14 ］が次\n第になくなり、死亡率は上昇する。そこで、この死亡率の変化を追跡でき\nるように［ 15 ］、経過年数別に死亡率を表示したものが「選択表」である。",
      "choices": [
        {
          "label": "ア",
          "text": "完全生命表"
        },
        {
          "label": "イ",
          "text": "基礎生命表"
        },
        {
          "label": "ウ",
          "text": "経験生命表"
        },
        {
          "label": "エ",
          "text": "告知効果"
        },
        {
          "label": "オ",
          "text": "全体生命表"
        },
        {
          "label": "カ",
          "text": "選択効果"
        },
        {
          "label": "キ",
          "text": "総合表"
        },
        {
          "label": "ク",
          "text": "地域別"
        },
        {
          "label": "ケ",
          "text": "統一表"
        },
        {
          "label": "コ",
          "text": "年齢別"
        }
      ],
      "answer": "カ",
      "answerText": "選択効果",
      "explanation": "空欄［14］は「選択効果」。本文の計算条件・用語定義に照らして、この選択肢が該当する。",
      "keyPoint": "空欄［14］は「選択効果」。計算問題では使用する付表・利率・丸め条件を確認する。",
      "commonMistake": "問題文の数値条件、付表番号、端数処理を読み落とさない。",
      "difficulty": "標準",
      "tags": [
        "2024年度",
        "フォームA",
        "生命保険計理"
      ],
      "chapter": "第1章 生命保険と死亡表",
      "section": "死亡表の種類",
      "evidence": {
        "textbook": "2026年版 生命保険講座 生命保険計理",
        "chapter": "第1章 生命保険と死亡表",
        "section": "死亡表の種類",
        "page": "4-17",
        "quote": "死亡表の種類に関する本文・例題・付表を根拠に確認。"
      }
    },
    {
      "id": "2024-A-seiho-keiri-015",
      "subject": "生命保険計理",
      "year": 2024,
      "form": "A",
      "questionNumber": 15,
      "category": "生命保険と死亡表",
      "questionType": "語群選択",
      "question": "次の文章の空欄［15］に入る最も適切なものを選んでください。\n\n［死亡表の種類］                                語群\n文中の空欄［ 11 ］～［ 15 ］に入る最も適切なものを選んでください。   ア．完全生命表\n\n死亡表は、国民あるいは特定地域の人口を対象として、その人口統計に       イ．基礎生命表\n\nよる死亡状況を表した「国民生命表」と、生命保険会社などの保険事業体       ウ．経験生命表\nが被保険者集団の実際の死亡統計に基づいて作成した「［ 11 ］」とに分け\nられる。                                    エ．告知効果\n\n「国民生命表」は、５年ごとの国勢調査による男女別、年齢別人口とそ       オ．全体生命表\nの時期の人口動態統計による男女別、年齢別死亡数を材料にして精緻な統\n計処理によって作成される「［ 12 ］」と、毎年の人口動態統計の死亡数と    カ．選択効果\n\n推計人口を用い、簡略化された計算によって算定された死亡率を表示する       キ．総合表\n「簡易生命表」とに分けられる。\n「\n［ 11 ］」は、経過年数による区別により、\n「［ 13 ］\n」と「選択表」とに   ク．地域別\n\n分けられる。                                  ケ．統一表\n「\n［ 13 ］」は、保険契約加入後の経過年数を考慮しないで全期間を対象\nに年齢別にまとめた死亡表であるが、生命保険会社では、健康状態等につ       コ．年齢別\n\nいての危険選択が行われた被保険者集団を対象としているので、一般には\n「国民生命表」よりも低い死亡率を示す。\nしかし、通常は加入後年数が経過するにつれて、それらの［ 14 ］が次\n第になくなり、死亡率は上昇する。そこで、この死亡率の変化を追跡でき\nるように［ 15 ］、経過年数別に死亡率を表示したものが「選択表」である。",
      "choices": [
        {
          "label": "ア",
          "text": "完全生命表"
        },
        {
          "label": "イ",
          "text": "基礎生命表"
        },
        {
          "label": "ウ",
          "text": "経験生命表"
        },
        {
          "label": "エ",
          "text": "告知効果"
        },
        {
          "label": "オ",
          "text": "全体生命表"
        },
        {
          "label": "カ",
          "text": "選択効果"
        },
        {
          "label": "キ",
          "text": "総合表"
        },
        {
          "label": "ク",
          "text": "地域別"
        },
        {
          "label": "ケ",
          "text": "統一表"
        },
        {
          "label": "コ",
          "text": "年齢別"
        }
      ],
      "answer": "コ",
      "answerText": "年齢別",
      "explanation": "空欄［15］は「年齢別」。本文の計算条件・用語定義に照らして、この選択肢が該当する。",
      "keyPoint": "空欄［15］は「年齢別」。計算問題では使用する付表・利率・丸め条件を確認する。",
      "commonMistake": "問題文の数値条件、付表番号、端数処理を読み落とさない。",
      "difficulty": "標準",
      "tags": [
        "2024年度",
        "フォームA",
        "生命保険計理"
      ],
      "chapter": "第1章 生命保険と死亡表",
      "section": "死亡表の種類",
      "evidence": {
        "textbook": "2026年版 生命保険講座 生命保険計理",
        "chapter": "第1章 生命保険と死亡表",
        "section": "死亡表の種類",
        "page": "4-17",
        "quote": "死亡表の種類に関する本文・例題・付表を根拠に確認。"
      }
    },
    {
      "id": "2024-A-seiho-keiri-016",
      "subject": "生命保険計理",
      "year": 2024,
      "form": "A",
      "questionNumber": 16,
      "category": "剰余金と契約者配当",
      "questionType": "語群選択",
      "question": "次の文章の空欄［16］に入る最も適切なものを選んでください。\n\n［契約者配当の意義と割当て］                          語群\n文中の空欄［ 16 ］～［ 20 ］に入る最も適切なものを選んでください。   ア．１年\n\nイ．３年\n生命保険の保険料は、保険期間を通じて［ 16 ］を考慮して設定された\n計算基礎によって算定されているため、生命保険会社の決算では、通常、       ウ．安全性\n剰余金（過剰分）が生ずる。\nそこで、予定の保険費用（営業保険料）と実際に要した保険費用（実質       エ．確実性\n保険料）との差額を調整するために剰余金（過剰分）を一定の基準で各契\nオ．公平性\n約に割り当て、分配するものが契約者配当金であり、過払いの保険料の割\n戻しに相当する性格をもつ。                           カ．収益性\n契約者配当の割当方法は多種多様であり、その具備すべき主な条件には、\nキ．損益別配当方式\n［ 17 ］、弾力性、実用性、大衆性があげられるが、互いに矛盾し合う側面\nもあり、その調和を実務面で考慮しなければならない。               ク．保険業法施行規則\n生命保険会社では、これらの諸条件を考慮し、これまで、死差、利差、費\n差による［ 18 ］を主体とした契約者配当の割当てを行っており、毎年の     ケ．保険法\n配当率を単年度の剰余金（過剰分）の大きさだけで決定するのではなく、\nコ．利源別配当方式（利源式）\n長期安定性を考慮して変動をできるだけ小幅にとどめるように努めている。\nなお、契約者配当の割当方式については、\n［ 19 ］において定められている。\n通常の有配当個人保険では契約者配当の割当ての対象となる契約を次の\nとおりとしている。\nア）決算事業年度末において契約日からその日を含めて［ 20 ］を超え\nている有効契約\nイ）次の事業年度中に保険期間の満了または契約応当日以後の死亡保険\n金、高度障害保険金の支払いにより消滅する契約\nウ）契約日から所定年数を経過した後に消滅する契約",
      "choices": [
        {
          "label": "ア",
          "text": "１年"
        },
        {
          "label": "イ",
          "text": "３年"
        },
        {
          "label": "ウ",
          "text": "安全性"
        },
        {
          "label": "エ",
          "text": "確実性"
        },
        {
          "label": "オ",
          "text": "公平性"
        },
        {
          "label": "カ",
          "text": "収益性"
        },
        {
          "label": "キ",
          "text": "損益別配当方式"
        },
        {
          "label": "ク",
          "text": "保険業法施行規則"
        },
        {
          "label": "ケ",
          "text": "保険法"
        },
        {
          "label": "コ",
          "text": "利源別配当方式（利源式）"
        }
      ],
      "answer": "ウ",
      "answerText": "安全性",
      "explanation": "空欄［16］は「安全性」。本文の計算条件・用語定義に照らして、この選択肢が該当する。",
      "keyPoint": "空欄［16］は「安全性」。計算問題では使用する付表・利率・丸め条件を確認する。",
      "commonMistake": "問題文の数値条件、付表番号、端数処理を読み落とさない。",
      "difficulty": "標準",
      "tags": [
        "2024年度",
        "フォームA",
        "生命保険計理"
      ],
      "chapter": "第6章 剰余金と契約者配当",
      "section": "契約者配当",
      "evidence": {
        "textbook": "2026年版 生命保険講座 生命保険計理",
        "chapter": "第6章 剰余金と契約者配当",
        "section": "契約者配当",
        "page": "130-141",
        "quote": "契約者配当に関する本文・例題・付表を根拠に確認。"
      }
    },
    {
      "id": "2024-A-seiho-keiri-017",
      "subject": "生命保険計理",
      "year": 2024,
      "form": "A",
      "questionNumber": 17,
      "category": "剰余金と契約者配当",
      "questionType": "語群選択",
      "question": "次の文章の空欄［17］に入る最も適切なものを選んでください。\n\n［契約者配当の意義と割当て］                          語群\n文中の空欄［ 16 ］～［ 20 ］に入る最も適切なものを選んでください。   ア．１年\n\nイ．３年\n生命保険の保険料は、保険期間を通じて［ 16 ］を考慮して設定された\n計算基礎によって算定されているため、生命保険会社の決算では、通常、       ウ．安全性\n剰余金（過剰分）が生ずる。\nそこで、予定の保険費用（営業保険料）と実際に要した保険費用（実質       エ．確実性\n保険料）との差額を調整するために剰余金（過剰分）を一定の基準で各契\nオ．公平性\n約に割り当て、分配するものが契約者配当金であり、過払いの保険料の割\n戻しに相当する性格をもつ。                           カ．収益性\n契約者配当の割当方法は多種多様であり、その具備すべき主な条件には、\nキ．損益別配当方式\n［ 17 ］、弾力性、実用性、大衆性があげられるが、互いに矛盾し合う側面\nもあり、その調和を実務面で考慮しなければならない。               ク．保険業法施行規則\n生命保険会社では、これらの諸条件を考慮し、これまで、死差、利差、費\n差による［ 18 ］を主体とした契約者配当の割当てを行っており、毎年の     ケ．保険法\n配当率を単年度の剰余金（過剰分）の大きさだけで決定するのではなく、\nコ．利源別配当方式（利源式）\n長期安定性を考慮して変動をできるだけ小幅にとどめるように努めている。\nなお、契約者配当の割当方式については、\n［ 19 ］において定められている。\n通常の有配当個人保険では契約者配当の割当ての対象となる契約を次の\nとおりとしている。\nア）決算事業年度末において契約日からその日を含めて［ 20 ］を超え\nている有効契約\nイ）次の事業年度中に保険期間の満了または契約応当日以後の死亡保険\n金、高度障害保険金の支払いにより消滅する契約\nウ）契約日から所定年数を経過した後に消滅する契約",
      "choices": [
        {
          "label": "ア",
          "text": "１年"
        },
        {
          "label": "イ",
          "text": "３年"
        },
        {
          "label": "ウ",
          "text": "安全性"
        },
        {
          "label": "エ",
          "text": "確実性"
        },
        {
          "label": "オ",
          "text": "公平性"
        },
        {
          "label": "カ",
          "text": "収益性"
        },
        {
          "label": "キ",
          "text": "損益別配当方式"
        },
        {
          "label": "ク",
          "text": "保険業法施行規則"
        },
        {
          "label": "ケ",
          "text": "保険法"
        },
        {
          "label": "コ",
          "text": "利源別配当方式（利源式）"
        }
      ],
      "answer": "オ",
      "answerText": "公平性",
      "explanation": "空欄［17］は「公平性」。本文の計算条件・用語定義に照らして、この選択肢が該当する。",
      "keyPoint": "空欄［17］は「公平性」。計算問題では使用する付表・利率・丸め条件を確認する。",
      "commonMistake": "問題文の数値条件、付表番号、端数処理を読み落とさない。",
      "difficulty": "標準",
      "tags": [
        "2024年度",
        "フォームA",
        "生命保険計理"
      ],
      "chapter": "第6章 剰余金と契約者配当",
      "section": "契約者配当",
      "evidence": {
        "textbook": "2026年版 生命保険講座 生命保険計理",
        "chapter": "第6章 剰余金と契約者配当",
        "section": "契約者配当",
        "page": "130-141",
        "quote": "契約者配当に関する本文・例題・付表を根拠に確認。"
      }
    },
    {
      "id": "2024-A-seiho-keiri-018",
      "subject": "生命保険計理",
      "year": 2024,
      "form": "A",
      "questionNumber": 18,
      "category": "剰余金と契約者配当",
      "questionType": "語群選択",
      "question": "次の文章の空欄［18］に入る最も適切なものを選んでください。\n\n［契約者配当の意義と割当て］                          語群\n文中の空欄［ 16 ］～［ 20 ］に入る最も適切なものを選んでください。   ア．１年\n\nイ．３年\n生命保険の保険料は、保険期間を通じて［ 16 ］を考慮して設定された\n計算基礎によって算定されているため、生命保険会社の決算では、通常、       ウ．安全性\n剰余金（過剰分）が生ずる。\nそこで、予定の保険費用（営業保険料）と実際に要した保険費用（実質       エ．確実性\n保険料）との差額を調整するために剰余金（過剰分）を一定の基準で各契\nオ．公平性\n約に割り当て、分配するものが契約者配当金であり、過払いの保険料の割\n戻しに相当する性格をもつ。                           カ．収益性\n契約者配当の割当方法は多種多様であり、その具備すべき主な条件には、\nキ．損益別配当方式\n［ 17 ］、弾力性、実用性、大衆性があげられるが、互いに矛盾し合う側面\nもあり、その調和を実務面で考慮しなければならない。               ク．保険業法施行規則\n生命保険会社では、これらの諸条件を考慮し、これまで、死差、利差、費\n差による［ 18 ］を主体とした契約者配当の割当てを行っており、毎年の     ケ．保険法\n配当率を単年度の剰余金（過剰分）の大きさだけで決定するのではなく、\nコ．利源別配当方式（利源式）\n長期安定性を考慮して変動をできるだけ小幅にとどめるように努めている。\nなお、契約者配当の割当方式については、\n［ 19 ］において定められている。\n通常の有配当個人保険では契約者配当の割当ての対象となる契約を次の\nとおりとしている。\nア）決算事業年度末において契約日からその日を含めて［ 20 ］を超え\nている有効契約\nイ）次の事業年度中に保険期間の満了または契約応当日以後の死亡保険\n金、高度障害保険金の支払いにより消滅する契約\nウ）契約日から所定年数を経過した後に消滅する契約",
      "choices": [
        {
          "label": "ア",
          "text": "１年"
        },
        {
          "label": "イ",
          "text": "３年"
        },
        {
          "label": "ウ",
          "text": "安全性"
        },
        {
          "label": "エ",
          "text": "確実性"
        },
        {
          "label": "オ",
          "text": "公平性"
        },
        {
          "label": "カ",
          "text": "収益性"
        },
        {
          "label": "キ",
          "text": "損益別配当方式"
        },
        {
          "label": "ク",
          "text": "保険業法施行規則"
        },
        {
          "label": "ケ",
          "text": "保険法"
        },
        {
          "label": "コ",
          "text": "利源別配当方式（利源式）"
        }
      ],
      "answer": "コ",
      "answerText": "利源別配当方式（利源式）",
      "explanation": "空欄［18］は「利源別配当方式（利源式）」。本文の計算条件・用語定義に照らして、この選択肢が該当する。",
      "keyPoint": "空欄［18］は「利源別配当方式（利源式）」。計算問題では使用する付表・利率・丸め条件を確認する。",
      "commonMistake": "問題文の数値条件、付表番号、端数処理を読み落とさない。",
      "difficulty": "標準",
      "tags": [
        "2024年度",
        "フォームA",
        "生命保険計理"
      ],
      "chapter": "第6章 剰余金と契約者配当",
      "section": "契約者配当",
      "evidence": {
        "textbook": "2026年版 生命保険講座 生命保険計理",
        "chapter": "第6章 剰余金と契約者配当",
        "section": "契約者配当",
        "page": "130-141",
        "quote": "契約者配当に関する本文・例題・付表を根拠に確認。"
      }
    },
    {
      "id": "2024-A-seiho-keiri-019",
      "subject": "生命保険計理",
      "year": 2024,
      "form": "A",
      "questionNumber": 19,
      "category": "剰余金と契約者配当",
      "questionType": "語群選択",
      "question": "次の文章の空欄［19］に入る最も適切なものを選んでください。\n\n［契約者配当の意義と割当て］                          語群\n文中の空欄［ 16 ］～［ 20 ］に入る最も適切なものを選んでください。   ア．１年\n\nイ．３年\n生命保険の保険料は、保険期間を通じて［ 16 ］を考慮して設定された\n計算基礎によって算定されているため、生命保険会社の決算では、通常、       ウ．安全性\n剰余金（過剰分）が生ずる。\nそこで、予定の保険費用（営業保険料）と実際に要した保険費用（実質       エ．確実性\n保険料）との差額を調整するために剰余金（過剰分）を一定の基準で各契\nオ．公平性\n約に割り当て、分配するものが契約者配当金であり、過払いの保険料の割\n戻しに相当する性格をもつ。                           カ．収益性\n契約者配当の割当方法は多種多様であり、その具備すべき主な条件には、\nキ．損益別配当方式\n［ 17 ］、弾力性、実用性、大衆性があげられるが、互いに矛盾し合う側面\nもあり、その調和を実務面で考慮しなければならない。               ク．保険業法施行規則\n生命保険会社では、これらの諸条件を考慮し、これまで、死差、利差、費\n差による［ 18 ］を主体とした契約者配当の割当てを行っており、毎年の     ケ．保険法\n配当率を単年度の剰余金（過剰分）の大きさだけで決定するのではなく、\nコ．利源別配当方式（利源式）\n長期安定性を考慮して変動をできるだけ小幅にとどめるように努めている。\nなお、契約者配当の割当方式については、\n［ 19 ］において定められている。\n通常の有配当個人保険では契約者配当の割当ての対象となる契約を次の\nとおりとしている。\nア）決算事業年度末において契約日からその日を含めて［ 20 ］を超え\nている有効契約\nイ）次の事業年度中に保険期間の満了または契約応当日以後の死亡保険\n金、高度障害保険金の支払いにより消滅する契約\nウ）契約日から所定年数を経過した後に消滅する契約",
      "choices": [
        {
          "label": "ア",
          "text": "１年"
        },
        {
          "label": "イ",
          "text": "３年"
        },
        {
          "label": "ウ",
          "text": "安全性"
        },
        {
          "label": "エ",
          "text": "確実性"
        },
        {
          "label": "オ",
          "text": "公平性"
        },
        {
          "label": "カ",
          "text": "収益性"
        },
        {
          "label": "キ",
          "text": "損益別配当方式"
        },
        {
          "label": "ク",
          "text": "保険業法施行規則"
        },
        {
          "label": "ケ",
          "text": "保険法"
        },
        {
          "label": "コ",
          "text": "利源別配当方式（利源式）"
        }
      ],
      "answer": "ク",
      "answerText": "保険業法施行規則",
      "explanation": "空欄［19］は「保険業法施行規則」。本文の計算条件・用語定義に照らして、この選択肢が該当する。",
      "keyPoint": "空欄［19］は「保険業法施行規則」。計算問題では使用する付表・利率・丸め条件を確認する。",
      "commonMistake": "問題文の数値条件、付表番号、端数処理を読み落とさない。",
      "difficulty": "標準",
      "tags": [
        "2024年度",
        "フォームA",
        "生命保険計理"
      ],
      "chapter": "第6章 剰余金と契約者配当",
      "section": "契約者配当",
      "evidence": {
        "textbook": "2026年版 生命保険講座 生命保険計理",
        "chapter": "第6章 剰余金と契約者配当",
        "section": "契約者配当",
        "page": "130-141",
        "quote": "契約者配当に関する本文・例題・付表を根拠に確認。"
      }
    },
    {
      "id": "2024-A-seiho-keiri-020",
      "subject": "生命保険計理",
      "year": 2024,
      "form": "A",
      "questionNumber": 20,
      "category": "剰余金と契約者配当",
      "questionType": "語群選択",
      "question": "次の文章の空欄［20］に入る最も適切なものを選んでください。\n\n［契約者配当の意義と割当て］                          語群\n文中の空欄［ 16 ］～［ 20 ］に入る最も適切なものを選んでください。   ア．１年\n\nイ．３年\n生命保険の保険料は、保険期間を通じて［ 16 ］を考慮して設定された\n計算基礎によって算定されているため、生命保険会社の決算では、通常、       ウ．安全性\n剰余金（過剰分）が生ずる。\nそこで、予定の保険費用（営業保険料）と実際に要した保険費用（実質       エ．確実性\n保険料）との差額を調整するために剰余金（過剰分）を一定の基準で各契\nオ．公平性\n約に割り当て、分配するものが契約者配当金であり、過払いの保険料の割\n戻しに相当する性格をもつ。                           カ．収益性\n契約者配当の割当方法は多種多様であり、その具備すべき主な条件には、\nキ．損益別配当方式\n［ 17 ］、弾力性、実用性、大衆性があげられるが、互いに矛盾し合う側面\nもあり、その調和を実務面で考慮しなければならない。               ク．保険業法施行規則\n生命保険会社では、これらの諸条件を考慮し、これまで、死差、利差、費\n差による［ 18 ］を主体とした契約者配当の割当てを行っており、毎年の     ケ．保険法\n配当率を単年度の剰余金（過剰分）の大きさだけで決定するのではなく、\nコ．利源別配当方式（利源式）\n長期安定性を考慮して変動をできるだけ小幅にとどめるように努めている。\nなお、契約者配当の割当方式については、\n［ 19 ］において定められている。\n通常の有配当個人保険では契約者配当の割当ての対象となる契約を次の\nとおりとしている。\nア）決算事業年度末において契約日からその日を含めて［ 20 ］を超え\nている有効契約\nイ）次の事業年度中に保険期間の満了または契約応当日以後の死亡保険\n金、高度障害保険金の支払いにより消滅する契約\nウ）契約日から所定年数を経過した後に消滅する契約",
      "choices": [
        {
          "label": "ア",
          "text": "１年"
        },
        {
          "label": "イ",
          "text": "３年"
        },
        {
          "label": "ウ",
          "text": "安全性"
        },
        {
          "label": "エ",
          "text": "確実性"
        },
        {
          "label": "オ",
          "text": "公平性"
        },
        {
          "label": "カ",
          "text": "収益性"
        },
        {
          "label": "キ",
          "text": "損益別配当方式"
        },
        {
          "label": "ク",
          "text": "保険業法施行規則"
        },
        {
          "label": "ケ",
          "text": "保険法"
        },
        {
          "label": "コ",
          "text": "利源別配当方式（利源式）"
        }
      ],
      "answer": "ア",
      "answerText": "１年",
      "explanation": "空欄［20］は「１年」。本文の計算条件・用語定義に照らして、この選択肢が該当する。",
      "keyPoint": "空欄［20］は「１年」。計算問題では使用する付表・利率・丸め条件を確認する。",
      "commonMistake": "問題文の数値条件、付表番号、端数処理を読み落とさない。",
      "difficulty": "標準",
      "tags": [
        "2024年度",
        "フォームA",
        "生命保険計理"
      ],
      "chapter": "第6章 剰余金と契約者配当",
      "section": "契約者配当",
      "evidence": {
        "textbook": "2026年版 生命保険講座 生命保険計理",
        "chapter": "第6章 剰余金と契約者配当",
        "section": "契約者配当",
        "page": "130-141",
        "quote": "契約者配当に関する本文・例題・付表を根拠に確認。"
      }
    },
    {
      "id": "2024-A-seiho-keiri-021",
      "subject": "生命保険計理",
      "year": 2024,
      "form": "A",
      "questionNumber": 21,
      "category": "現価と終価",
      "questionType": "正しいものを1つ選ぶ",
      "question": "［ 21 ］死亡保険金の現価                            男子 41 歳加入、保険期間５年、保険金 400 万円の養老保険の、５年後に支\n男子 41 歳加入、保険期間５年、保険金 400 万円の養老保険の、５年間に支   払う満期保険金の現価について、正しい数値を１つ選んでください（計算\n払う死亡保険金の現価について、正しい数値を１つ選んでください（計算         過程および計算結果は千円未満四捨五入）\n。計算にあたっては、＜付表１＞\n過程および計算結果は千円未満四捨五入）\n。計算にあたっては、適宜、＜付         の生保標準生命表 2018（死亡保険用）\n（男）の生存数、＜付表２＞の複利表・\n表１＞の生保標準生命表 2018（死亡保険用）\n（男）の死亡数、＜付表２＞の      複利現価表（年 1.0％）を使用してください。\n複利表・複利現価表（年 1.0％）を使用してください。\n\nア．369,187,837千円\nア．2,887,038千円\nイ．369,907,146千円\nイ．2,964,000千円\nウ．370,561,754千円\nウ．3,132,291千円",
      "choices": [
        {
          "label": "ア",
          "text": "369,187,837千円"
        },
        {
          "label": "イ",
          "text": "369,907,146千円"
        },
        {
          "label": "ウ",
          "text": "370,561,754千円"
        }
      ],
      "answer": "ア",
      "answerText": "369,187,837千円",
      "explanation": "正解は「ア」。設問「死亡保険金の現価                            男子 41 歳加入、保険期間５年、保険金 400 万円の養老保険の、５年後に支」について、本文の定義・計算原理に照らすとこの選択肢が正答となる。",
      "keyPoint": "「死亡保険金の現価                            男子 41 歳加入、保険期間５年、保険金 400 万円の養老保険の、５年後に支」は現価と終価の論点。用語定義と計算条件をセットで確認する。",
      "commonMistake": "選択肢の一部だけで判断せず、数値条件・用語の対応関係まで確認する。",
      "difficulty": "標準",
      "tags": [
        "2024年度",
        "フォームA",
        "生命保険計理"
      ],
      "chapter": "第2章 現価と終価",
      "section": "現価と終価",
      "evidence": {
        "textbook": "2026年版 生命保険講座 生命保険計理",
        "chapter": "第2章 現価と終価",
        "section": "現価と終価",
        "page": "26-31",
        "quote": "現価と終価に関する本文・例題・付表を根拠に確認。"
      }
    },
    {
      "id": "2024-A-seiho-keiri-022",
      "subject": "生命保険計理",
      "year": 2024,
      "form": "A",
      "questionNumber": 22,
      "category": "生命保険計理",
      "questionType": "正しいものを1つ選ぶ",
      "question": "要確認",
      "choices": [
        {
          "label": "ア",
          "text": "選択肢ア"
        },
        {
          "label": "イ",
          "text": "選択肢イ"
        },
        {
          "label": "ウ",
          "text": "選択肢ウ"
        }
      ],
      "answer": "イ",
      "answerText": "選択肢イ",
      "explanation": "正解は「イ」。設問「問題22」について、本文の定義・計算原理に照らすとこの選択肢が正答となる。",
      "keyPoint": "「問題22」は要確認の論点。用語定義と計算条件をセットで確認する。",
      "commonMistake": "選択肢の一部だけで判断せず、数値条件・用語の対応関係まで確認する。",
      "difficulty": "標準",
      "tags": [
        "2024年度",
        "フォームA",
        "生命保険計理"
      ],
      "chapter": "要確認",
      "section": "要確認",
      "evidence": {
        "textbook": "2026年版 生命保険講座 生命保険計理",
        "chapter": "要確認",
        "section": "要確認",
        "page": "要確認",
        "quote": "要確認に関する本文・例題・付表を根拠に確認。"
      }
    },
    {
      "id": "2024-A-seiho-keiri-023",
      "subject": "生命保険計理",
      "year": 2024,
      "form": "A",
      "questionNumber": 23,
      "category": "現価と終価",
      "questionType": "正しいものを1つ選ぶ",
      "question": "［ 23 ］予定事業費の現価                            ［ 24 ］養老保険の年払営業保険料\n男子 41 歳加入、保険期間５年、保険金 400 万円の養老保険の予定事業費の   男子 41 歳加入、保険期間５年、保険金 400 万円の養老保険の年払営業保険\n現価について、正しい数値を１つ選んでください（計算過程および計算結         料について、正しい数値を１つ選んでください（計算過程の収入は小数第\n果は千円未満四捨五入）\n。計算にあたっては、＜付表１＞の生保標準生命表         １位四捨五入、支出は千円未満四捨五入、計算結果は 10 円未満四捨五入）。\n2018（死亡保険用）\n（男）の生存数を使用してください。なお、保険料払込       計算にあたっては、＜付表１＞の生保標準生命表 2018（死亡保険用）\n（男）\n免除のための保険料は考慮しないものとし、予定事業費率は保険金比例の         の生存数・死亡数、＜付表２＞の複利表・複利現価表（年 1.0％）を使用し\n予定新契約費（保険金千円につき 25 円）のみとします。              てください。なお、保険料払込免除のための保険料は考慮しないものとし、\n予定事業費率は保険金比例の予定新契約費（保険金千円につき 25 円）のみ\n\nア．9,744,994千円                             とします。\n\nイ．9,781,000千円\nア．798,050円\nウ．9,793,600千円\nイ．799,140円\n\nウ．801,860円",
      "choices": [
        {
          "label": "ア",
          "text": "9,744,994千円                             とします。"
        },
        {
          "label": "イ",
          "text": "9,781,000千円"
        },
        {
          "label": "ウ",
          "text": "9,793,600千円"
        }
      ],
      "answer": "ウ",
      "answerText": "9,793,600千円",
      "explanation": "正解は「ウ」。設問「予定事業費の現価                            ［ 24 ］養老保険の年払営業保険料」について、本文の定義・計算原理に照らすとこの選択肢が正答となる。",
      "keyPoint": "「予定事業費の現価                            ［ 24 ］養老保険の年払営業保険料」は現価と終価の論点。用語定義と計算条件をセットで確認する。",
      "commonMistake": "選択肢の一部だけで判断せず、数値条件・用語の対応関係まで確認する。",
      "difficulty": "標準",
      "tags": [
        "2024年度",
        "フォームA",
        "生命保険計理"
      ],
      "chapter": "第2章 現価と終価",
      "section": "現価と終価",
      "evidence": {
        "textbook": "2026年版 生命保険講座 生命保険計理",
        "chapter": "第2章 現価と終価",
        "section": "現価と終価",
        "page": "26-31",
        "quote": "現価と終価に関する本文・例題・付表を根拠に確認。"
      }
    },
    {
      "id": "2024-A-seiho-keiri-024",
      "subject": "生命保険計理",
      "year": 2024,
      "form": "A",
      "questionNumber": 24,
      "category": "生命保険計理",
      "questionType": "正しいものを1つ選ぶ",
      "question": "要確認",
      "choices": [
        {
          "label": "ア",
          "text": "選択肢ア"
        },
        {
          "label": "イ",
          "text": "選択肢イ"
        },
        {
          "label": "ウ",
          "text": "選択肢ウ"
        }
      ],
      "answer": "イ",
      "answerText": "選択肢イ",
      "explanation": "正解は「イ」。設問「問題24」について、本文の定義・計算原理に照らすとこの選択肢が正答となる。",
      "keyPoint": "「問題24」は要確認の論点。用語定義と計算条件をセットで確認する。",
      "commonMistake": "選択肢の一部だけで判断せず、数値条件・用語の対応関係まで確認する。",
      "difficulty": "標準",
      "tags": [
        "2024年度",
        "フォームA",
        "生命保険計理"
      ],
      "chapter": "要確認",
      "section": "要確認",
      "evidence": {
        "textbook": "2026年版 生命保険講座 生命保険計理",
        "chapter": "要確認",
        "section": "要確認",
        "page": "要確認",
        "quote": "要確認に関する本文・例題・付表を根拠に確認。"
      }
    },
    {
      "id": "2024-A-seiho-keiri-025",
      "subject": "生命保険計理",
      "year": 2024,
      "form": "A",
      "questionNumber": 25,
      "category": "解約返戻金と契約変更",
      "questionType": "正しいものを1つ選ぶ",
      "question": "［ 25 ］払済保険金額                                ＜ここからは誤っているものを選ぶ問題です。＞\n男子 30 歳加入、保険期間 30 年、保険金 300 万円の養老保険で保険料払込   ［ 26 ］計算基礎の変化と純保険料の変化\n（経過）年数が 10 年、この時点の解約返戻金が 858,000 円で、この契約を   次の文章のうち、誤っているものを１つ選んでください。\n払済保険に変更した場合の払済保険金について、正しい数値を１つ選んで\nください（男子 40 歳加入、保険期間 20 年、保険金 300 万円の養老保険の   ア．予定死亡率と予定利率を低くすると、生存保険の純保険料は低くなる。\n一時払保険料は、2,345,580 円、予定利率は元契約と同じ 1.5％、予定新契\n約費はゼロ、維持費は保険金千円につき２円、計算結果は千円未満四捨五           イ．予定死亡率を低く、予定利率を高くすると、定期保険と養老保険の純\n入）\n。                                           保険料は低くなる。\n\nア．1,097,000円                                ウ．予定死亡率を変えずに、予定利率を高くすると、定期保険と養老保険\nの純保険料は低くなる。\nイ．1,100,000円\n\nウ．1,126,000円",
      "choices": [
        {
          "label": "ア",
          "text": "予定死亡率と予定利率を低くすると、生存保険の純保険料は低くなる。"
        },
        {
          "label": "イ",
          "text": "予定死亡率を低く、予定利率を高くすると、定期保険と養老保険の純"
        },
        {
          "label": "ウ",
          "text": "予定死亡率を変えずに、予定利率を高くすると、定期保険と養老保険"
        }
      ],
      "answer": "ア",
      "answerText": "予定死亡率と予定利率を低くすると、生存保険の純保険料は低くなる。",
      "explanation": "正解は「ア」。設問「払済保険金額                                ＜ここからは誤っているものを選ぶ問題です。＞」について、本文の定義・計算原理に照らすとこの選択肢が正答となる。",
      "keyPoint": "「払済保険金額                                ＜ここからは誤っているものを選ぶ問題です。＞」は払済保険の論点。用語定義と計算条件をセットで確認する。",
      "commonMistake": "選択肢の一部だけで判断せず、数値条件・用語の対応関係まで確認する。",
      "difficulty": "標準",
      "tags": [
        "2024年度",
        "フォームA",
        "生命保険計理"
      ],
      "chapter": "第5章 解約返戻金と契約変更",
      "section": "払済保険",
      "evidence": {
        "textbook": "2026年版 生命保険講座 生命保険計理",
        "chapter": "第5章 解約返戻金と契約変更",
        "section": "払済保険",
        "page": "112-113",
        "quote": "払済保険に関する本文・例題・付表を根拠に確認。"
      }
    },
    {
      "id": "2024-A-seiho-keiri-026",
      "subject": "生命保険計理",
      "year": 2024,
      "form": "A",
      "questionNumber": 26,
      "category": "生命保険計理",
      "questionType": "誤っているものを1つ選ぶ",
      "question": "要確認",
      "choices": [
        {
          "label": "ア",
          "text": "選択肢ア"
        },
        {
          "label": "イ",
          "text": "選択肢イ"
        },
        {
          "label": "ウ",
          "text": "選択肢ウ"
        }
      ],
      "answer": "ア",
      "answerText": "選択肢ア",
      "explanation": "正解は「ア」。設問「問題26」について、本文の定義・計算原理に照らすとこの選択肢が正答となる。",
      "keyPoint": "「問題26」は要確認の論点。用語定義と計算条件をセットで確認する。",
      "commonMistake": "選択肢の一部だけで判断せず、数値条件・用語の対応関係まで確認する。",
      "difficulty": "標準",
      "tags": [
        "2024年度",
        "フォームA",
        "生命保険計理"
      ],
      "chapter": "要確認",
      "section": "要確認",
      "evidence": {
        "textbook": "2026年版 生命保険講座 生命保険計理",
        "chapter": "要確認",
        "section": "要確認",
        "page": "要確認",
        "quote": "要確認に関する本文・例題・付表を根拠に確認。"
      }
    },
    {
      "id": "2024-A-seiho-keiri-027",
      "subject": "生命保険計理",
      "year": 2024,
      "form": "A",
      "questionNumber": 27,
      "category": "保険料",
      "questionType": "誤っているものを1つ選ぶ",
      "question": "［ 27 ］営業保険料                         ［ 28 ］事業年度末責任準備金\n次の文章のうち、誤っているものを１つ選んでください。          次の文章のうち、誤っているものを１つ選んでください。\n\nア．付加保険料の計算に使用する予定事業費率の決め方は、保険金に比例   ア．保険業法上、生命保険会社は、事業年度末までに経過した期間に見合\nさせる方式が一般的である。                       う保険料部分に対応する積立金（保険料積立金）\n、翌事業年度以降に対応\nする保険料部分（未経過保険料）および危険準備金の３区分に分けて計\nイ．最近では高額割引制度を実施している生命保険会社も多い。この制度    算することになっている。\nは、高額契約について営業保険料を割引くものであり、通常は、保険金\nランクを何段階かに分けて割引く方法が採られている。          イ．未経過保険料は、事業年度内に最後に払い込まれた保険料の有効期間\n末が事業年度末を超える期間（未経過期間）に応じ、比例的に算出され\nウ．営業保険料の計算において、保険種類によって異なる計算基礎（予定    る。かつては、未経過期間は保険料有効期間の平均１/２であるとして、\n死亡率など）を用いたり、また他社との競争上、保険料率を調整したり    保険料の半分とすることも多かった。\nすることがあり、保険種類間でアンバランスが生ずることがあるので、\n状況に応じて調整を行う必要がある。                  ウ．危険準備金は、\n「保険リスク」\n、「第三分野保険の保険リスク」、\n「予定利\n率リスク」および「最低保証リスク」に備えるものとされている。",
      "choices": [
        {
          "label": "ア",
          "text": "付加保険料の計算に使用する予定事業費率の決め方は、保険金に比例"
        },
        {
          "label": "イ",
          "text": "最近では高額割引制度を実施している生命保険会社も多い。この制度    算することになっている。"
        },
        {
          "label": "ウ",
          "text": "営業保険料の計算において、保険種類によって異なる計算基礎（予定    る。かつては、未経過期間は保険料有効期間の平均１/２であるとして、"
        }
      ],
      "answer": "ア",
      "answerText": "付加保険料の計算に使用する予定事業費率の決め方は、保険金に比例",
      "explanation": "正解は「ア」。設問「営業保険料                         ［ 28 ］事業年度末責任準備金」について、本文の定義・計算原理に照らすとこの選択肢が正答となる。",
      "keyPoint": "「営業保険料                         ［ 28 ］事業年度末責任準備金」は保険料の論点。用語定義と計算条件をセットで確認する。",
      "commonMistake": "選択肢の一部だけで判断せず、数値条件・用語の対応関係まで確認する。",
      "difficulty": "標準",
      "tags": [
        "2024年度",
        "フォームA",
        "生命保険計理"
      ],
      "chapter": "第3章 保険料",
      "section": "保険料",
      "evidence": {
        "textbook": "2026年版 生命保険講座 生命保険計理",
        "chapter": "第3章 保険料",
        "section": "保険料",
        "page": "33-63",
        "quote": "保険料に関する本文・例題・付表を根拠に確認。"
      }
    },
    {
      "id": "2024-A-seiho-keiri-028",
      "subject": "生命保険計理",
      "year": 2024,
      "form": "A",
      "questionNumber": 28,
      "category": "生命保険計理",
      "questionType": "誤っているものを1つ選ぶ",
      "question": "要確認",
      "choices": [
        {
          "label": "ア",
          "text": "選択肢ア"
        },
        {
          "label": "イ",
          "text": "選択肢イ"
        },
        {
          "label": "ウ",
          "text": "選択肢ウ"
        }
      ],
      "answer": "ア",
      "answerText": "選択肢ア",
      "explanation": "正解は「ア」。設問「問題28」について、本文の定義・計算原理に照らすとこの選択肢が正答となる。",
      "keyPoint": "「問題28」は要確認の論点。用語定義と計算条件をセットで確認する。",
      "commonMistake": "選択肢の一部だけで判断せず、数値条件・用語の対応関係まで確認する。",
      "difficulty": "標準",
      "tags": [
        "2024年度",
        "フォームA",
        "生命保険計理"
      ],
      "chapter": "要確認",
      "section": "要確認",
      "evidence": {
        "textbook": "2026年版 生命保険講座 生命保険計理",
        "chapter": "要確認",
        "section": "要確認",
        "page": "要確認",
        "quote": "要確認に関する本文・例題・付表を根拠に確認。"
      }
    },
    {
      "id": "2024-A-seiho-keiri-029",
      "subject": "生命保険計理",
      "year": 2024,
      "form": "A",
      "questionNumber": 29,
      "category": "変額保険のあらまし",
      "questionType": "誤っているものを1つ選ぶ",
      "question": "［ 29 ］契約転換制度                         ［ 30 ］変額保険の仕組み\n次の文章のうち、誤っているものを１つ選んでください。           次の文章のうち、誤っているものを１つ選んでください。\n\nア．転換方式が加入年齢方式（責任準備金差額払込み型）の場合、転換後    ア．特約保険料、前納保険料、体況による特別条件付契約の割増保険料は\n契約の保険料は転換前契約の加入時の年齢による保険料に、転換時の責     一般勘定で管理される。\n任準備金差額を分割して払い込む分を加えたものとなる。\nイ．特別勘定に入った貯蓄保険料部分は積立金として運用され、積立金は\nイ．転換方式が到達年齢方式（転換前責任準備金分割保険料充当型）の場     毎月の運用実績（評価損益を含む総合収益）によって計算される特別勘\n合、転換後契約の保険料は転換時の到達年齢（保険年齢）によって計算     定指数（インデックス）またはユニット価格の変化に応じて毎月変動す\nするが、転換前契約の責任準備金をこの保険料（の一部）に分割充当す     る。\nる。\nウ．定期保険特約や災害・疾病関係特約等に基づく保険金や給付金は、保\nウ．転換方式が到達年齢方式（一時払保険購入型）の場合、転換後契約の     険期間を通じて契約当初のままで変動しない。\n保険料は転換時の到達年齢（保険年齢）によって計算するが、転換前契\n約の責任準備金を転換後契約の一時払保険料（新契約費部分を含むもの）\nに充当し、転換後契約は新規の払込保険部分と一時払保険部分とで構成\nする。\n\n＜ここからは正誤を選ぶ問題です。＞                    33［平準保険料］\n31［生命保険契約と年齢］                        次の文章について、正しい場合には「正」\n、誤っている場合には「誤」を選\n次の文章について、正しい場合には「正」\n、誤っている場合には「誤」を選    んでください。\nんでください。\n平準保険料とは、毎年の保険料を一定額とし、１年ごとの比較では各年\n契約年齢の計算には、満ⅹ歳を中心に前後６カ月の被保険者に対してⅹ    の保険料収入が保険金支払に見合わなくても、保険期間が満了した際に全\n歳の保険料率を適用する四捨五入方式である「保険年齢方式」と、通常の    体の収支がつりあうように計算された保険料である。\n年齢の数え方と同じで、端数月はすべて切り捨てる切捨方式である「満年\n齢方式」がある。                             正\n誤\n正\n誤\n34［分割払営業保険料］\n次の文章について、正しい場合には「正」\n、誤っている場合には「誤」を選\n32［現価］                               んでください。\n次の文章について、正しい場合には「正」\n、誤っている場合には「誤」を選\nんでください。                               １年分を何回かに分けて払い込む分割払営業保険料の年間払込額は、年\n間の予定利息分や事業費の増加により、年払とした場合の営業保険料額を\n将来のある時期に、ある一定の金額を受け取るために現在投資しなければ   下回る。\nならない金額を現価といい、その支払時点によって期始払、期央払、期末払\nの３つに分けられる。通常、単に現価という場合には期始払現価を指す。    正\n誤\n正\n誤\n\n35［責任準備金積立根拠］                        37［剰余金処分］\n次の文章について、正しい場合には「正」\n、誤っている場合には「誤」を選    次の文章について、正しい場合には「正」\n、誤っている場合には「誤」を選\nんでください。                              んでください。\n\n保険料が自然保険料方式で計算されている場合、平準保険料方式と同様、    株式会社形態の生命保険会社の場合、\n「契約者配当準備金繰入額」として\n毎保険年度末に将来の保険金支払いに備えて責任準備金を積み立てる必要    契約者への配当財源を先取りした後、株主総会等における「剰余金処分に\nがある。                                 関する決議書」によって、\n「繰越利益剰余金」から、株主配当金、退職給付\n積立金、別途積立金等が処分され、残額が次年度へ繰り越される。\n正\n誤                                    正\n誤\n\n36［延長保険］\n次の文章について、正しい場合には「正」\n、誤っている場合には「誤」を選    38［その他の損益］\nんでください。                              次の文章について、正しい場合には「正」\n、誤っている場合には「誤」を選\nんでください。\n保険料の払い込みが困難となった場合、そのときの解約返戻金を定期保\n険の一時払保険料に充当することにより延長保険に変更することができる。    価格変動損益は、有価証券および動産・不動産の売却益と評価益の合計\nこの場合、死亡保険金額は変わらないが、保険期間が短くなることもあり、   額から、それら財産の売却損と評価損の合計額を差し引き、さらに保険業\n満期時に受け取る保険金もゼロまたは少額になる。              法によって価格変動準備金として積み立てる額を除いたものである。\n\n正                                    正\n誤                                    誤\n\n39［リスクヘッジ］                          ＜ここからは適切な組み合わせを選ぶ問題です。＞\n次の文章について、正しい場合には「正」\n、誤っている場合には「誤」を選   41［資産の平均利回り］\nんでください。                             次の文章について、下線部ＡまたはＢのいずれかが誤っている場合と、Ａ・\nＢともに正しい場合とがあります。ＡまたはＢのいずれかが誤っている場\n特別勘定の選択は契約者の自己責任であり投資のリスクは契約者が負担   合は、誤っている記号と代わって入るものが最も適切な組み合わせを選択\nするが、最低保証部分のリスクは生命保険会社が取らなければならない。   してください。Ａ・Ｂともに正しい場合は、記号Ｃを選択してください。\n\n正                                    資産の年間平均利回りを概算する公式に(A)ハーディの公式があるが、資\n誤                                   産の増減が年間を通じてほぼ一様になっていない場合には、この公式を用\nいることは適切ではない。この欠点を避けたものとして(B)平均残高方式が\n用いられるようになった。\n40［団体定期保険の数理］\n次の文章について、正しい場合には「正」\n、誤っている場合には「誤」を選\nんでください。\n\nア．Ａ－相互扶助\n団体定期保険は、保険料が被保険者ごとの積み上げを基礎としているの\nで、配当についても被保険者ごとに算出し、それを積み上げた団体単位で   イ．Ａ－チルメル\n\n計算されている。                            ウ．Ｂ－超過資産加算方式\n\n正                                   エ．Ｂ－一時払積増方式\n\n誤                                   オ．Ｃ（Ａ・Ｂともに正しい）\n\n42［保険料の計算原理］                          43［準備金の積立根拠］\n次の文章について、下線部ＡまたはＢのいずれかが誤っている場合と、Ａ・    次の文章について、下線部ＡまたはＢのいずれかが誤っている場合と、Ａ・\nＢともに正しい場合とがあります。ＡまたはＢのいずれかが誤っている場     Ｂともに正しい場合とがあります。ＡまたはＢのいずれかが誤っている場\n合は、誤っている記号と代わって入るものが最も適切な組み合わせを選択     合は、誤っている記号と代わって入るものが最も適切な組み合わせを選択\nしてください。Ａ・Ｂともに正しい場合は、記号Ｃを選択してください。     してください。Ａ・Ｂともに正しい場合は、記号Ｃを選択してください。\n\n保険料の計算は利息計算における(A)終価の考え方を用いて保険期間の     生命保険会社に毎年払い込まれる(A)純保険料からその年の保険金支払\n(B)始期に保険期間を通じての収支を割戻し、その時点で収支相等の原則が   いに回した残りの部分は、将来の保険金支払いまたは満期保険金の支払い\n成立するように収入・支出それぞれの(A)終価を等しくおいて行われる。    のために積み立てられるべき金額であり、各年の残額を累積したものが(B)\n責任準備金である。\n\nア．Ａ－現価\nア．Ａ－付加保険料\nイ．Ａ－年平均利回り\nイ．Ａ－定期保険料\nウ．Ｂ－満期\nウ．Ｂ－ソルベンシー・マージン\nエ．Ｂ－末期\nエ．Ｂ－危険準備金\nオ．Ｃ（Ａ・Ｂともに正しい）\nオ．Ｃ（Ａ・Ｂともに正しい）\n\n44［危険保険料の計算］                         45［積立に関する法的規制］\n次の文章について、下線部ＡまたはＢのいずれかが誤っている場合と、Ａ・   次の文章について、下線部ＡまたはＢのいずれかが誤っている場合と、Ａ・\nＢともに正しい場合とがあります。ＡまたはＢのいずれかが誤っている場    Ｂともに正しい場合とがあります。ＡまたはＢのいずれかが誤っている場\n合は、誤っている記号と代わって入るものが最も適切な組み合わせを選択    合は、誤っている記号と代わって入るものが最も適切な組み合わせを選択\nしてください。Ａ・Ｂともに正しい場合は、記号Ｃを選択してください。    してください。Ａ・Ｂともに正しい場合は、記号Ｃを選択してください。\n\n危険保険料の一般的な計算式は、次のとおりである。             責任準備金の積み立てにあたって、保険料積立金は(A)最低責任準備金の\n危険保険料 ＝（(A)危険保険金）×（年間死亡者数／年始生存者数）   対象契約については(A)最低責任準備金、それ以外の契約については(B)平\n×（１／(B)（１＋予定利率）1/12 乗）       準純保険料式責任準備金を下回ることができない。ただし、\n（保険会社が設\n立間もない場合など）特別の事情がある場合についてはこの限りではない。\n\nア．Ａ－死亡保険金\nア．Ａ－最高\nイ．Ａ－年度末保険料積立金\nイ．Ａ－標準\nウ．Ｂ－（１＋予定利率）1/2乗\nウ．Ｂ－チルメル\nエ．Ｂ－（１＋予定利率）\nエ．Ｂ－平均保険料\nオ．Ｃ（Ａ・Ｂともに正しい）\nオ．Ｃ（Ａ・Ｂともに正しい）\n\n46［解約返戻金］                             47［利源分析］\n次の文章について、下線部ＡまたはＢのいずれかが誤っている場合と、Ａ・    次の文章について、下線部ＡまたはＢのいずれかが誤っている場合と、Ａ・\nＢともに正しい場合とがあります。ＡまたはＢのいずれかが誤っている場     Ｂともに正しい場合とがあります。ＡまたはＢのいずれかが誤っている場\n合は、誤っている記号と代わって入るものが最も適切な組み合わせを選択     合は、誤っている記号と代わって入るものが最も適切な組み合わせを選択\nしてください。Ａ・Ｂともに正しい場合は、記号Ｃを選択してください。     してください。Ａ・Ｂともに正しい場合は、記号Ｃを選択してください。\n\n解約返戻金は、解約の場合だけでなく、契約者に契約継続の意思が全く      剰余金を発生源（利源）別に大別（利源分析）すると、次の４つに分けら\nなくて(A)払済保険に変更した契約についても、契約者の請求に応じて支払   れる。\nわれる。また、(B)契約者貸付の限度基準としても用いられている。      ①死差益 ＝（予定死亡率－実際死亡率）× (A)死亡保険金額\n②利差益 ＝（実際利回り－予定利率）× (B)責任準備金の総額\n③費差益 ＝ 付加保険料の総額 － 実際事業費の総額\n④その他の損益\n\nア．Ａ－契約転換\n\nイ．Ａ－失効\n\nウ．Ｂ－配当支払い                             ア．Ａ－危険保険金額\n\nエ．Ｂ－保険料払込猶予期間                         イ．Ａ－基本保険金額\n\nオ．Ｃ（Ａ・Ｂともに正しい）                        ウ．Ｂ－資産運用収入\n\nエ．Ｂ－貯蓄保険料の総額\n\nオ．Ｃ（Ａ・Ｂともに正しい）\n\n48［配当金の計算方法］                            49［特別勘定の位置付け］\n次の文章について、下線部ＡまたはＢのいずれかが誤っている場合と、Ａ・      次の文章について、下線部ＡまたはＢのいずれかが誤っている場合と、Ａ・\nＢともに正しい場合とがあります。ＡまたはＢのいずれかが誤っている場       Ｂともに正しい場合とがあります。ＡまたはＢのいずれかが誤っている場\n合は、誤っている記号と代わって入るものが最も適切な組み合わせを選択       合は、誤っている記号と代わって入るものが最も適切な組み合わせを選択\nしてください。Ａ・Ｂともに正しい場合は、記号Ｃを選択してください。       してください。Ａ・Ｂともに正しい場合は、記号Ｃを選択してください。\n\n現在採用している通常の有配当契約（主契約部分）における契約者配当        特別勘定の位置付けについて、保険業法には、保険会社は「(A)運用実績\n金（通常配当金）の計算内容は、およそ次のとおりである。             連動型保険契約」その他の内閣府令で定める保険契約について、当該保険\n①死差益配当 ＝ 死差益配当率 ×（保険金－(A)保険年度末保険料積立金）   契約に係る資産をその他の資産と区別して経理するため、特別勘定を設け\n②利差益配当 ＝ 利差益配当率 × (A)保険年度末保険料積立金        なければならないと定められている。また、特別勘定は、内閣府令で定め\n③費差益配当 ＝ 費差益配当率 × (B)保険金                る場合を除き、一般勘定（特別勘定以外の勘定）または他の特別勘定との\n振替(B)をしなければならない。\n\nア．Ａ－既払込保険料累計額\nア．Ａ－運用実績非連動型\nイ．Ａ－既払込保険料累計額×２\nイ．Ａ－積立型\nウ．Ｂ－契約者配当準備金\nウ．Ｂ－が認められている\nエ．Ｂ－消滅時保険料積立金\nエ．Ｂ－を禁止されている\nオ．Ｃ（Ａ・Ｂともに正しい）\nオ．Ｃ（Ａ・Ｂともに正しい）\n\n50［団体年金の財政方式］\n次の文章について、下線部ＡまたはＢのいずれかが誤っている場合と、Ａ・\nＢともに正しい場合とがあります。ＡまたはＢのいずれかが誤っている場\n合は、誤っている記号と代わって入るものが最も適切な組み合わせを選択\nしてください。Ａ・Ｂともに正しい場合は、記号Ｃを選択してください。\n\n団体年金制度の財政方式の一つに、各種給付額をまかなうのに必要な原\n資を加入期間にわたって平準的に積み立てる平準積立方式があり、その平\n準化の方法によって、(A)加入年齢方式、到達年齢方式、(B)保険料前納方\n式（閉鎖型）等に細分される。\n\nア．Ａ－即時積立\n\nイ．Ａ－加入時年金現価積立\n\nウ．Ｂ－総合保険料\n\nエ．Ｂ－平準保険料\n\nオ．Ｃ（Ａ・Ｂともに正しい）\n\ncopyright (c) The Life Insurance Association of Japan, All rights reserved.",
      "choices": [
        {
          "label": "ア",
          "text": "転換方式が加入年齢方式（責任準備金差額払込み型）の場合、転換後"
        },
        {
          "label": "イ",
          "text": "特別勘定に入った貯蓄保険料部分は積立金として運用され、積立金は"
        },
        {
          "label": "ウ",
          "text": "定期保険特約や災害・疾病関係特約等に基づく保険金や給付金は、保"
        },
        {
          "label": "エ",
          "text": "Ｂ－一時払積増方式"
        },
        {
          "label": "オ",
          "text": "Ｃ（Ａ・Ｂともに正しい）"
        }
      ],
      "answer": "ウ",
      "answerText": "定期保険特約や災害・疾病関係特約等に基づく保険金や給付金は、保",
      "explanation": "正解は「ウ」。設問「契約転換制度                         ［ 30 ］変額保険の仕組み」について、本文の定義・計算原理に照らすとこの選択肢が正答となる。",
      "keyPoint": "「契約転換制度                         ［ 30 ］変額保険の仕組み」は変額保険の論点。用語定義と計算条件をセットで確認する。",
      "commonMistake": "選択肢の一部だけで判断せず、数値条件・用語の対応関係まで確認する。",
      "difficulty": "標準",
      "tags": [
        "2024年度",
        "フォームA",
        "生命保険計理"
      ],
      "chapter": "第7章 変額保険のあらまし",
      "section": "変額保険",
      "evidence": {
        "textbook": "2026年版 生命保険講座 生命保険計理",
        "chapter": "第7章 変額保険のあらまし",
        "section": "変額保険",
        "page": "143-152",
        "quote": "変額保険に関する本文・例題・付表を根拠に確認。"
      }
    },
    {
      "id": "2024-A-seiho-keiri-030",
      "subject": "生命保険計理",
      "year": 2024,
      "form": "A",
      "questionNumber": 30,
      "category": "生命保険計理",
      "questionType": "誤っているものを1つ選ぶ",
      "question": "要確認",
      "choices": [
        {
          "label": "ア",
          "text": "選択肢ア"
        },
        {
          "label": "イ",
          "text": "選択肢イ"
        },
        {
          "label": "ウ",
          "text": "選択肢ウ"
        }
      ],
      "answer": "イ",
      "answerText": "選択肢イ",
      "explanation": "正解は「イ」。設問「問題30」について、本文の定義・計算原理に照らすとこの選択肢が正答となる。",
      "keyPoint": "「問題30」は要確認の論点。用語定義と計算条件をセットで確認する。",
      "commonMistake": "選択肢の一部だけで判断せず、数値条件・用語の対応関係まで確認する。",
      "difficulty": "標準",
      "tags": [
        "2024年度",
        "フォームA",
        "生命保険計理"
      ],
      "chapter": "要確認",
      "section": "要確認",
      "evidence": {
        "textbook": "2026年版 生命保険講座 生命保険計理",
        "chapter": "要確認",
        "section": "要確認",
        "page": "要確認",
        "quote": "要確認に関する本文・例題・付表を根拠に確認。"
      }
    },
    {
      "id": "2024-A-seiho-keiri-031",
      "subject": "生命保険計理",
      "year": 2024,
      "form": "A",
      "questionNumber": 31,
      "category": "生命保険計理",
      "questionType": "正誤問題",
      "question": "要確認",
      "choices": [
        {
          "label": "正",
          "text": "正"
        },
        {
          "label": "誤",
          "text": "誤"
        }
      ],
      "answer": "正",
      "answerText": "正",
      "explanation": "この記述は「正」。設問「問題31」について、本文の定義・計算原理と一致するかで判定する。",
      "keyPoint": "「問題31」は要確認の論点。用語定義と計算条件をセットで確認する。",
      "commonMistake": "選択肢の一部だけで判断せず、数値条件・用語の対応関係まで確認する。",
      "difficulty": "標準",
      "tags": [
        "2024年度",
        "フォームA",
        "生命保険計理"
      ],
      "chapter": "要確認",
      "section": "要確認",
      "evidence": {
        "textbook": "2026年版 生命保険講座 生命保険計理",
        "chapter": "要確認",
        "section": "要確認",
        "page": "要確認",
        "quote": "要確認に関する本文・例題・付表を根拠に確認。"
      }
    },
    {
      "id": "2024-A-seiho-keiri-032",
      "subject": "生命保険計理",
      "year": 2024,
      "form": "A",
      "questionNumber": 32,
      "category": "生命保険計理",
      "questionType": "正誤問題",
      "question": "要確認",
      "choices": [
        {
          "label": "正",
          "text": "正"
        },
        {
          "label": "誤",
          "text": "誤"
        }
      ],
      "answer": "誤",
      "answerText": "誤",
      "explanation": "この記述は「誤」。設問「問題32」について、本文の定義・計算原理と一致するかで判定する。",
      "keyPoint": "「問題32」は要確認の論点。用語定義と計算条件をセットで確認する。",
      "commonMistake": "選択肢の一部だけで判断せず、数値条件・用語の対応関係まで確認する。",
      "difficulty": "標準",
      "tags": [
        "2024年度",
        "フォームA",
        "生命保険計理"
      ],
      "chapter": "要確認",
      "section": "要確認",
      "evidence": {
        "textbook": "2026年版 生命保険講座 生命保険計理",
        "chapter": "要確認",
        "section": "要確認",
        "page": "要確認",
        "quote": "要確認に関する本文・例題・付表を根拠に確認。"
      }
    },
    {
      "id": "2024-A-seiho-keiri-033",
      "subject": "生命保険計理",
      "year": 2024,
      "form": "A",
      "questionNumber": 33,
      "category": "生命保険計理",
      "questionType": "正誤問題",
      "question": "要確認",
      "choices": [
        {
          "label": "正",
          "text": "正"
        },
        {
          "label": "誤",
          "text": "誤"
        }
      ],
      "answer": "正",
      "answerText": "正",
      "explanation": "この記述は「正」。設問「問題33」について、本文の定義・計算原理と一致するかで判定する。",
      "keyPoint": "「問題33」は要確認の論点。用語定義と計算条件をセットで確認する。",
      "commonMistake": "選択肢の一部だけで判断せず、数値条件・用語の対応関係まで確認する。",
      "difficulty": "標準",
      "tags": [
        "2024年度",
        "フォームA",
        "生命保険計理"
      ],
      "chapter": "要確認",
      "section": "要確認",
      "evidence": {
        "textbook": "2026年版 生命保険講座 生命保険計理",
        "chapter": "要確認",
        "section": "要確認",
        "page": "要確認",
        "quote": "要確認に関する本文・例題・付表を根拠に確認。"
      }
    },
    {
      "id": "2024-A-seiho-keiri-034",
      "subject": "生命保険計理",
      "year": 2024,
      "form": "A",
      "questionNumber": 34,
      "category": "生命保険計理",
      "questionType": "正誤問題",
      "question": "要確認",
      "choices": [
        {
          "label": "正",
          "text": "正"
        },
        {
          "label": "誤",
          "text": "誤"
        }
      ],
      "answer": "誤",
      "answerText": "誤",
      "explanation": "この記述は「誤」。設問「問題34」について、本文の定義・計算原理と一致するかで判定する。",
      "keyPoint": "「問題34」は要確認の論点。用語定義と計算条件をセットで確認する。",
      "commonMistake": "選択肢の一部だけで判断せず、数値条件・用語の対応関係まで確認する。",
      "difficulty": "標準",
      "tags": [
        "2024年度",
        "フォームA",
        "生命保険計理"
      ],
      "chapter": "要確認",
      "section": "要確認",
      "evidence": {
        "textbook": "2026年版 生命保険講座 生命保険計理",
        "chapter": "要確認",
        "section": "要確認",
        "page": "要確認",
        "quote": "要確認に関する本文・例題・付表を根拠に確認。"
      }
    },
    {
      "id": "2024-A-seiho-keiri-035",
      "subject": "生命保険計理",
      "year": 2024,
      "form": "A",
      "questionNumber": 35,
      "category": "生命保険計理",
      "questionType": "正誤問題",
      "question": "要確認",
      "choices": [
        {
          "label": "正",
          "text": "正"
        },
        {
          "label": "誤",
          "text": "誤"
        }
      ],
      "answer": "誤",
      "answerText": "誤",
      "explanation": "この記述は「誤」。設問「問題35」について、本文の定義・計算原理と一致するかで判定する。",
      "keyPoint": "「問題35」は要確認の論点。用語定義と計算条件をセットで確認する。",
      "commonMistake": "選択肢の一部だけで判断せず、数値条件・用語の対応関係まで確認する。",
      "difficulty": "標準",
      "tags": [
        "2024年度",
        "フォームA",
        "生命保険計理"
      ],
      "chapter": "要確認",
      "section": "要確認",
      "evidence": {
        "textbook": "2026年版 生命保険講座 生命保険計理",
        "chapter": "要確認",
        "section": "要確認",
        "page": "要確認",
        "quote": "要確認に関する本文・例題・付表を根拠に確認。"
      }
    },
    {
      "id": "2024-A-seiho-keiri-036",
      "subject": "生命保険計理",
      "year": 2024,
      "form": "A",
      "questionNumber": 36,
      "category": "生命保険計理",
      "questionType": "正誤問題",
      "question": "要確認",
      "choices": [
        {
          "label": "正",
          "text": "正"
        },
        {
          "label": "誤",
          "text": "誤"
        }
      ],
      "answer": "正",
      "answerText": "正",
      "explanation": "この記述は「正」。設問「問題36」について、本文の定義・計算原理と一致するかで判定する。",
      "keyPoint": "「問題36」は要確認の論点。用語定義と計算条件をセットで確認する。",
      "commonMistake": "選択肢の一部だけで判断せず、数値条件・用語の対応関係まで確認する。",
      "difficulty": "標準",
      "tags": [
        "2024年度",
        "フォームA",
        "生命保険計理"
      ],
      "chapter": "要確認",
      "section": "要確認",
      "evidence": {
        "textbook": "2026年版 生命保険講座 生命保険計理",
        "chapter": "要確認",
        "section": "要確認",
        "page": "要確認",
        "quote": "要確認に関する本文・例題・付表を根拠に確認。"
      }
    },
    {
      "id": "2024-A-seiho-keiri-037",
      "subject": "生命保険計理",
      "year": 2024,
      "form": "A",
      "questionNumber": 37,
      "category": "生命保険計理",
      "questionType": "正誤問題",
      "question": "要確認",
      "choices": [
        {
          "label": "正",
          "text": "正"
        },
        {
          "label": "誤",
          "text": "誤"
        }
      ],
      "answer": "正",
      "answerText": "正",
      "explanation": "この記述は「正」。設問「問題37」について、本文の定義・計算原理と一致するかで判定する。",
      "keyPoint": "「問題37」は要確認の論点。用語定義と計算条件をセットで確認する。",
      "commonMistake": "選択肢の一部だけで判断せず、数値条件・用語の対応関係まで確認する。",
      "difficulty": "標準",
      "tags": [
        "2024年度",
        "フォームA",
        "生命保険計理"
      ],
      "chapter": "要確認",
      "section": "要確認",
      "evidence": {
        "textbook": "2026年版 生命保険講座 生命保険計理",
        "chapter": "要確認",
        "section": "要確認",
        "page": "要確認",
        "quote": "要確認に関する本文・例題・付表を根拠に確認。"
      }
    },
    {
      "id": "2024-A-seiho-keiri-038",
      "subject": "生命保険計理",
      "year": 2024,
      "form": "A",
      "questionNumber": 38,
      "category": "生命保険計理",
      "questionType": "正誤問題",
      "question": "要確認",
      "choices": [
        {
          "label": "正",
          "text": "正"
        },
        {
          "label": "誤",
          "text": "誤"
        }
      ],
      "answer": "正",
      "answerText": "正",
      "explanation": "この記述は「正」。設問「問題38」について、本文の定義・計算原理と一致するかで判定する。",
      "keyPoint": "「問題38」は要確認の論点。用語定義と計算条件をセットで確認する。",
      "commonMistake": "選択肢の一部だけで判断せず、数値条件・用語の対応関係まで確認する。",
      "difficulty": "標準",
      "tags": [
        "2024年度",
        "フォームA",
        "生命保険計理"
      ],
      "chapter": "要確認",
      "section": "要確認",
      "evidence": {
        "textbook": "2026年版 生命保険講座 生命保険計理",
        "chapter": "要確認",
        "section": "要確認",
        "page": "要確認",
        "quote": "要確認に関する本文・例題・付表を根拠に確認。"
      }
    },
    {
      "id": "2024-A-seiho-keiri-039",
      "subject": "生命保険計理",
      "year": 2024,
      "form": "A",
      "questionNumber": 39,
      "category": "生命保険計理",
      "questionType": "正誤問題",
      "question": "要確認",
      "choices": [
        {
          "label": "正",
          "text": "正"
        },
        {
          "label": "誤",
          "text": "誤"
        }
      ],
      "answer": "正",
      "answerText": "正",
      "explanation": "この記述は「正」。設問「問題39」について、本文の定義・計算原理と一致するかで判定する。",
      "keyPoint": "「問題39」は要確認の論点。用語定義と計算条件をセットで確認する。",
      "commonMistake": "選択肢の一部だけで判断せず、数値条件・用語の対応関係まで確認する。",
      "difficulty": "標準",
      "tags": [
        "2024年度",
        "フォームA",
        "生命保険計理"
      ],
      "chapter": "要確認",
      "section": "要確認",
      "evidence": {
        "textbook": "2026年版 生命保険講座 生命保険計理",
        "chapter": "要確認",
        "section": "要確認",
        "page": "要確認",
        "quote": "要確認に関する本文・例題・付表を根拠に確認。"
      }
    },
    {
      "id": "2024-A-seiho-keiri-040",
      "subject": "生命保険計理",
      "year": 2024,
      "form": "A",
      "questionNumber": 40,
      "category": "生命保険計理",
      "questionType": "正誤問題",
      "question": "要確認",
      "choices": [
        {
          "label": "正",
          "text": "正"
        },
        {
          "label": "誤",
          "text": "誤"
        }
      ],
      "answer": "誤",
      "answerText": "誤",
      "explanation": "この記述は「誤」。設問「問題40」について、本文の定義・計算原理と一致するかで判定する。",
      "keyPoint": "「問題40」は要確認の論点。用語定義と計算条件をセットで確認する。",
      "commonMistake": "選択肢の一部だけで判断せず、数値条件・用語の対応関係まで確認する。",
      "difficulty": "標準",
      "tags": [
        "2024年度",
        "フォームA",
        "生命保険計理"
      ],
      "chapter": "要確認",
      "section": "要確認",
      "evidence": {
        "textbook": "2026年版 生命保険講座 生命保険計理",
        "chapter": "要確認",
        "section": "要確認",
        "page": "要確認",
        "quote": "要確認に関する本文・例題・付表を根拠に確認。"
      }
    },
    {
      "id": "2024-A-seiho-keiri-041",
      "subject": "生命保険計理",
      "year": 2024,
      "form": "A",
      "questionNumber": 41,
      "category": "生命保険計理",
      "questionType": "組み合わせ選択",
      "question": "要確認",
      "choices": [
        {
          "label": "ア",
          "text": "選択肢ア"
        },
        {
          "label": "イ",
          "text": "選択肢イ"
        },
        {
          "label": "ウ",
          "text": "選択肢ウ"
        },
        {
          "label": "エ",
          "text": "選択肢エ"
        },
        {
          "label": "オ",
          "text": "Ｃ（Ａ・Ｂともに正しい）"
        }
      ],
      "answer": "オ",
      "answerText": "Ｃ（Ａ・Ｂともに正しい）",
      "explanation": "正解は「オ」。設問「問題41」について、本文の定義・計算原理に照らすとこの選択肢が正答となる。",
      "keyPoint": "「問題41」は要確認の論点。用語定義と計算条件をセットで確認する。",
      "commonMistake": "選択肢の一部だけで判断せず、数値条件・用語の対応関係まで確認する。",
      "difficulty": "標準",
      "tags": [
        "2024年度",
        "フォームA",
        "生命保険計理"
      ],
      "chapter": "要確認",
      "section": "要確認",
      "evidence": {
        "textbook": "2026年版 生命保険講座 生命保険計理",
        "chapter": "要確認",
        "section": "要確認",
        "page": "要確認",
        "quote": "要確認に関する本文・例題・付表を根拠に確認。"
      }
    },
    {
      "id": "2024-A-seiho-keiri-042",
      "subject": "生命保険計理",
      "year": 2024,
      "form": "A",
      "questionNumber": 42,
      "category": "生命保険計理",
      "questionType": "組み合わせ選択",
      "question": "要確認",
      "choices": [
        {
          "label": "ア",
          "text": "選択肢ア"
        },
        {
          "label": "イ",
          "text": "選択肢イ"
        },
        {
          "label": "ウ",
          "text": "選択肢ウ"
        },
        {
          "label": "エ",
          "text": "選択肢エ"
        },
        {
          "label": "オ",
          "text": "Ｃ（Ａ・Ｂともに正しい）"
        }
      ],
      "answer": "ア",
      "answerText": "選択肢ア",
      "explanation": "正解は「ア」。設問「問題42」について、本文の定義・計算原理に照らすとこの選択肢が正答となる。",
      "keyPoint": "「問題42」は要確認の論点。用語定義と計算条件をセットで確認する。",
      "commonMistake": "選択肢の一部だけで判断せず、数値条件・用語の対応関係まで確認する。",
      "difficulty": "標準",
      "tags": [
        "2024年度",
        "フォームA",
        "生命保険計理"
      ],
      "chapter": "要確認",
      "section": "要確認",
      "evidence": {
        "textbook": "2026年版 生命保険講座 生命保険計理",
        "chapter": "要確認",
        "section": "要確認",
        "page": "要確認",
        "quote": "要確認に関する本文・例題・付表を根拠に確認。"
      }
    },
    {
      "id": "2024-A-seiho-keiri-043",
      "subject": "生命保険計理",
      "year": 2024,
      "form": "A",
      "questionNumber": 43,
      "category": "生命保険計理",
      "questionType": "組み合わせ選択",
      "question": "要確認",
      "choices": [
        {
          "label": "ア",
          "text": "選択肢ア"
        },
        {
          "label": "イ",
          "text": "選択肢イ"
        },
        {
          "label": "ウ",
          "text": "選択肢ウ"
        },
        {
          "label": "エ",
          "text": "選択肢エ"
        },
        {
          "label": "オ",
          "text": "Ｃ（Ａ・Ｂともに正しい）"
        }
      ],
      "answer": "オ",
      "answerText": "Ｃ（Ａ・Ｂともに正しい）",
      "explanation": "正解は「オ」。設問「問題43」について、本文の定義・計算原理に照らすとこの選択肢が正答となる。",
      "keyPoint": "「問題43」は要確認の論点。用語定義と計算条件をセットで確認する。",
      "commonMistake": "選択肢の一部だけで判断せず、数値条件・用語の対応関係まで確認する。",
      "difficulty": "標準",
      "tags": [
        "2024年度",
        "フォームA",
        "生命保険計理"
      ],
      "chapter": "要確認",
      "section": "要確認",
      "evidence": {
        "textbook": "2026年版 生命保険講座 生命保険計理",
        "chapter": "要確認",
        "section": "要確認",
        "page": "要確認",
        "quote": "要確認に関する本文・例題・付表を根拠に確認。"
      }
    },
    {
      "id": "2024-A-seiho-keiri-044",
      "subject": "生命保険計理",
      "year": 2024,
      "form": "A",
      "questionNumber": 44,
      "category": "生命保険計理",
      "questionType": "組み合わせ選択",
      "question": "要確認",
      "choices": [
        {
          "label": "ア",
          "text": "選択肢ア"
        },
        {
          "label": "イ",
          "text": "選択肢イ"
        },
        {
          "label": "ウ",
          "text": "選択肢ウ"
        },
        {
          "label": "エ",
          "text": "選択肢エ"
        },
        {
          "label": "オ",
          "text": "Ｃ（Ａ・Ｂともに正しい）"
        }
      ],
      "answer": "ウ",
      "answerText": "選択肢ウ",
      "explanation": "正解は「ウ」。設問「問題44」について、本文の定義・計算原理に照らすとこの選択肢が正答となる。",
      "keyPoint": "「問題44」は要確認の論点。用語定義と計算条件をセットで確認する。",
      "commonMistake": "選択肢の一部だけで判断せず、数値条件・用語の対応関係まで確認する。",
      "difficulty": "標準",
      "tags": [
        "2024年度",
        "フォームA",
        "生命保険計理"
      ],
      "chapter": "要確認",
      "section": "要確認",
      "evidence": {
        "textbook": "2026年版 生命保険講座 生命保険計理",
        "chapter": "要確認",
        "section": "要確認",
        "page": "要確認",
        "quote": "要確認に関する本文・例題・付表を根拠に確認。"
      }
    },
    {
      "id": "2024-A-seiho-keiri-045",
      "subject": "生命保険計理",
      "year": 2024,
      "form": "A",
      "questionNumber": 45,
      "category": "生命保険計理",
      "questionType": "組み合わせ選択",
      "question": "要確認",
      "choices": [
        {
          "label": "ア",
          "text": "選択肢ア"
        },
        {
          "label": "イ",
          "text": "選択肢イ"
        },
        {
          "label": "ウ",
          "text": "選択肢ウ"
        },
        {
          "label": "エ",
          "text": "選択肢エ"
        },
        {
          "label": "オ",
          "text": "Ｃ（Ａ・Ｂともに正しい）"
        }
      ],
      "answer": "イ",
      "answerText": "選択肢イ",
      "explanation": "正解は「イ」。設問「問題45」について、本文の定義・計算原理に照らすとこの選択肢が正答となる。",
      "keyPoint": "「問題45」は要確認の論点。用語定義と計算条件をセットで確認する。",
      "commonMistake": "選択肢の一部だけで判断せず、数値条件・用語の対応関係まで確認する。",
      "difficulty": "標準",
      "tags": [
        "2024年度",
        "フォームA",
        "生命保険計理"
      ],
      "chapter": "要確認",
      "section": "要確認",
      "evidence": {
        "textbook": "2026年版 生命保険講座 生命保険計理",
        "chapter": "要確認",
        "section": "要確認",
        "page": "要確認",
        "quote": "要確認に関する本文・例題・付表を根拠に確認。"
      }
    },
    {
      "id": "2024-A-seiho-keiri-046",
      "subject": "生命保険計理",
      "year": 2024,
      "form": "A",
      "questionNumber": 46,
      "category": "生命保険計理",
      "questionType": "組み合わせ選択",
      "question": "要確認",
      "choices": [
        {
          "label": "ア",
          "text": "選択肢ア"
        },
        {
          "label": "イ",
          "text": "選択肢イ"
        },
        {
          "label": "ウ",
          "text": "選択肢ウ"
        },
        {
          "label": "エ",
          "text": "選択肢エ"
        },
        {
          "label": "オ",
          "text": "Ｃ（Ａ・Ｂともに正しい）"
        }
      ],
      "answer": "イ",
      "answerText": "選択肢イ",
      "explanation": "正解は「イ」。設問「問題46」について、本文の定義・計算原理に照らすとこの選択肢が正答となる。",
      "keyPoint": "「問題46」は要確認の論点。用語定義と計算条件をセットで確認する。",
      "commonMistake": "選択肢の一部だけで判断せず、数値条件・用語の対応関係まで確認する。",
      "difficulty": "標準",
      "tags": [
        "2024年度",
        "フォームA",
        "生命保険計理"
      ],
      "chapter": "要確認",
      "section": "要確認",
      "evidence": {
        "textbook": "2026年版 生命保険講座 生命保険計理",
        "chapter": "要確認",
        "section": "要確認",
        "page": "要確認",
        "quote": "要確認に関する本文・例題・付表を根拠に確認。"
      }
    },
    {
      "id": "2024-A-seiho-keiri-047",
      "subject": "生命保険計理",
      "year": 2024,
      "form": "A",
      "questionNumber": 47,
      "category": "生命保険計理",
      "questionType": "組み合わせ選択",
      "question": "要確認",
      "choices": [
        {
          "label": "ア",
          "text": "選択肢ア"
        },
        {
          "label": "イ",
          "text": "選択肢イ"
        },
        {
          "label": "ウ",
          "text": "選択肢ウ"
        },
        {
          "label": "エ",
          "text": "選択肢エ"
        },
        {
          "label": "オ",
          "text": "Ｃ（Ａ・Ｂともに正しい）"
        }
      ],
      "answer": "ア",
      "answerText": "選択肢ア",
      "explanation": "正解は「ア」。設問「問題47」について、本文の定義・計算原理に照らすとこの選択肢が正答となる。",
      "keyPoint": "「問題47」は要確認の論点。用語定義と計算条件をセットで確認する。",
      "commonMistake": "選択肢の一部だけで判断せず、数値条件・用語の対応関係まで確認する。",
      "difficulty": "標準",
      "tags": [
        "2024年度",
        "フォームA",
        "生命保険計理"
      ],
      "chapter": "要確認",
      "section": "要確認",
      "evidence": {
        "textbook": "2026年版 生命保険講座 生命保険計理",
        "chapter": "要確認",
        "section": "要確認",
        "page": "要確認",
        "quote": "要確認に関する本文・例題・付表を根拠に確認。"
      }
    },
    {
      "id": "2024-A-seiho-keiri-048",
      "subject": "生命保険計理",
      "year": 2024,
      "form": "A",
      "questionNumber": 48,
      "category": "生命保険計理",
      "questionType": "組み合わせ選択",
      "question": "要確認",
      "choices": [
        {
          "label": "ア",
          "text": "選択肢ア"
        },
        {
          "label": "イ",
          "text": "選択肢イ"
        },
        {
          "label": "ウ",
          "text": "選択肢ウ"
        },
        {
          "label": "エ",
          "text": "選択肢エ"
        },
        {
          "label": "オ",
          "text": "Ｃ（Ａ・Ｂともに正しい）"
        }
      ],
      "answer": "オ",
      "answerText": "Ｃ（Ａ・Ｂともに正しい）",
      "explanation": "正解は「オ」。設問「問題48」について、本文の定義・計算原理に照らすとこの選択肢が正答となる。",
      "keyPoint": "「問題48」は要確認の論点。用語定義と計算条件をセットで確認する。",
      "commonMistake": "選択肢の一部だけで判断せず、数値条件・用語の対応関係まで確認する。",
      "difficulty": "標準",
      "tags": [
        "2024年度",
        "フォームA",
        "生命保険計理"
      ],
      "chapter": "要確認",
      "section": "要確認",
      "evidence": {
        "textbook": "2026年版 生命保険講座 生命保険計理",
        "chapter": "要確認",
        "section": "要確認",
        "page": "要確認",
        "quote": "要確認に関する本文・例題・付表を根拠に確認。"
      }
    },
    {
      "id": "2024-A-seiho-keiri-049",
      "subject": "生命保険計理",
      "year": 2024,
      "form": "A",
      "questionNumber": 49,
      "category": "生命保険計理",
      "questionType": "組み合わせ選択",
      "question": "要確認",
      "choices": [
        {
          "label": "ア",
          "text": "選択肢ア"
        },
        {
          "label": "イ",
          "text": "選択肢イ"
        },
        {
          "label": "ウ",
          "text": "選択肢ウ"
        },
        {
          "label": "エ",
          "text": "選択肢エ"
        },
        {
          "label": "オ",
          "text": "Ｃ（Ａ・Ｂともに正しい）"
        }
      ],
      "answer": "エ",
      "answerText": "選択肢エ",
      "explanation": "正解は「エ」。設問「問題49」について、本文の定義・計算原理に照らすとこの選択肢が正答となる。",
      "keyPoint": "「問題49」は要確認の論点。用語定義と計算条件をセットで確認する。",
      "commonMistake": "選択肢の一部だけで判断せず、数値条件・用語の対応関係まで確認する。",
      "difficulty": "標準",
      "tags": [
        "2024年度",
        "フォームA",
        "生命保険計理"
      ],
      "chapter": "要確認",
      "section": "要確認",
      "evidence": {
        "textbook": "2026年版 生命保険講座 生命保険計理",
        "chapter": "要確認",
        "section": "要確認",
        "page": "要確認",
        "quote": "要確認に関する本文・例題・付表を根拠に確認。"
      }
    },
    {
      "id": "2024-A-seiho-keiri-050",
      "subject": "生命保険計理",
      "year": 2024,
      "form": "A",
      "questionNumber": 50,
      "category": "生命保険計理",
      "questionType": "組み合わせ選択",
      "question": "要確認",
      "choices": [
        {
          "label": "ア",
          "text": "選択肢ア"
        },
        {
          "label": "イ",
          "text": "選択肢イ"
        },
        {
          "label": "ウ",
          "text": "選択肢ウ"
        },
        {
          "label": "エ",
          "text": "選択肢エ"
        },
        {
          "label": "オ",
          "text": "Ｃ（Ａ・Ｂともに正しい）"
        }
      ],
      "answer": "ウ",
      "answerText": "選択肢ウ",
      "explanation": "正解は「ウ」。設問「問題50」について、本文の定義・計算原理に照らすとこの選択肢が正答となる。",
      "keyPoint": "「問題50」は要確認の論点。用語定義と計算条件をセットで確認する。",
      "commonMistake": "選択肢の一部だけで判断せず、数値条件・用語の対応関係まで確認する。",
      "difficulty": "標準",
      "tags": [
        "2024年度",
        "フォームA",
        "生命保険計理"
      ],
      "chapter": "要確認",
      "section": "要確認",
      "evidence": {
        "textbook": "2026年版 生命保険講座 生命保険計理",
        "chapter": "要確認",
        "section": "要確認",
        "page": "要確認",
        "quote": "要確認に関する本文・例題・付表を根拠に確認。"
      }
    }
  ]
}